{"frameRate":30,"name":"effect_1","version":"5.5","compatibleVersion":"5.5","armature":[{"type":"Armature","frameRate":30,"name":"armatureName","aabb":{"x":-215.77,"y":-175.13,"width":514.78,"height":354.99},"bone":[{"name":"root"},{"name":"t_10","parent":"root","transform":{"x":-105.01,"y":40.42,"skX":180,"skY":180,"scX":0.5,"scY":0.5}},{"name":"t_11","parent":"root","transform":{"x":-220.51,"y":-25.95,"skX":180,"skY":180,"scX":0.5,"scY":0.5}},{"name":"t_12","parent":"root","transform":{"x":-208,"y":28.74,"skX":180,"skY":180,"scX":0.5,"scY":0.5}},{"name":"t_13","parent":"root","transform":{"x":-26.24,"y":103.01,"skX":90,"skY":90,"scX":0.497,"scY":0.5}},{"name":"t_14","parent":"root","transform":{"x":26.95,"y":103.01,"skX":90,"skY":90,"scX":0.5,"scY":0.5}},{"name":"t_15","parent":"root","transform":{"x":38.56,"y":179.4,"skX":90,"skY":90,"scX":0.5,"scY":0.5}},{"name":"t_16","parent":"root","transform":{"x":-26.24,"y":209.74,"skX":90,"skY":90,"scX":0.5,"scY":0.5}},{"name":"t_17","parent":"root","transform":{"x":26.95,"y":209.74,"skX":90,"skY":90,"scX":0.5,"scY":0.5}},{"name":"t_18","parent":"root","transform":{"x":188.24,"y":-37,"scX":0.5,"scY":0.5}},{"name":"t_19","parent":"root","transform":{"x":241.44,"y":-37,"scX":0.5,"scY":0.5}},{"name":"t_20","parent":"root","transform":{"x":253.05,"y":39.39,"scX":0.5,"scY":0.5}},{"name":"t_21","parent":"root","transform":{"x":325.34,"y":24.09,"scX":0.5,"scY":0.5}},{"name":"t_22","parent":"root","transform":{"x":353.96,"y":-29.55,"scX":0.5,"scY":0.5}},{"name":"t_3","parent":"root","transform":{"x":-24.09,"y":-174.65,"skX":-87.63,"skY":-87.63,"scX":0.5,"scY":0.5}},{"name":"t_4","parent":"root","transform":{"x":29.1,"y":-174.65,"skX":-87.63,"skY":-87.63,"scX":0.5,"scY":0.5}},{"name":"t_5","parent":"root","transform":{"x":40.71,"y":-98.25,"skX":-87.63,"skY":-87.63,"scX":0.5,"scY":0.5}},{"name":"t_6","parent":"root","transform":{"x":-21.69,"y":-232.82,"skX":-87.63,"skY":-87.63,"scX":0.5,"scY":0.5}},{"name":"t_7","parent":"root","transform":{"x":31.5,"y":-232.82,"skX":-87.63,"skY":-87.63,"scX":0.5,"scY":0.5}},{"name":"t_8","parent":"root","transform":{"x":-169.81,"y":-35.96,"skX":180,"skY":180,"scX":0.5,"scY":0.5}},{"name":"t_9","parent":"root","transform":{"x":-116.61,"y":-35.96,"skX":180,"skY":180,"scX":0.5,"scY":0.5}},{"name":"y_1","parent":"root","transform":{"x":3.06,"y":-73.94,"scX":0.543,"scY":0.543}},{"name":"y_2","parent":"root","transform":{"x":-3.56,"y":-64.35,"scX":0.543,"scY":0.543}},{"name":"y_3","parent":"root","transform":{"x":6.51,"y":-61.46,"scX":0.543,"scY":0.543}},{"name":"y_4","parent":"root","transform":{"x":-7.34,"y":-75.74,"scX":0.543,"scY":0.543}}],"slot":[{"displayIndex":1,"name":"yjn_7","parent":"t_3"},{"displayIndex":-1,"name":"yjn_11","parent":"t_6"},{"displayIndex":1,"name":"yjn_21","parent":"t_8"},{"displayIndex":-1,"name":"yjn_24","parent":"t_11"},{"displayIndex":1,"name":"yjn_26","parent":"t_13"},{"displayIndex":-1,"name":"yjn_29","parent":"t_16"},{"displayIndex":1,"name":"yjn_31","parent":"t_18"},{"displayIndex":-1,"name":"yjn_34","parent":"t_21"},{"displayIndex":1,"name":"yjn_9","parent":"t_4"},{"displayIndex":-1,"name":"yjn_12","parent":"t_7"},{"displayIndex":1,"name":"yjn_22","parent":"t_9"},{"displayIndex":-1,"name":"yjn_25","parent":"t_12"},{"displayIndex":1,"name":"yjn_27","parent":"t_14"},{"displayIndex":-1,"name":"yjn_30","parent":"t_17"},{"displayIndex":1,"name":"yjn_32","parent":"t_19"},{"displayIndex":-1,"name":"yjn_35","parent":"t_22"},{"displayIndex":1,"name":"yjn_10","parent":"t_5"},{"displayIndex":1,"name":"yjn_23","parent":"t_10"},{"displayIndex":1,"name":"yjn_28","parent":"t_15"},{"displayIndex":1,"name":"yjn_33","parent":"t_20"},{"name":"yjn_8","parent":"y_1","color":{"aM":56}},{"name":"yjn_13","parent":"y_2","color":{"aM":56}},{"name":"yjn_14","parent":"y_3","color":{"aM":56}},{"name":"yjn_15","parent":"y_4","color":{"aM":56}}],"skin":[{"slot":[{"name":"yjn_7","display":[{"name":"yjn_5","transform":{"x":-64.45,"y":3.16}},{"name":"yjn_6","transform":{"x":-39.08,"y":-0.28}},{"name":"yjn_7","transform":{"x":-39.03,"y":0.58}}]},{"name":"yjn_25","display":[{"name":"yjn_5","transform":{"x":-64.45,"y":3.16}},{"name":"yjn_6","transform":{"x":-39.08,"y":-0.28}},{"name":"yjn_7","transform":{"x":-39.03,"y":0.58}}]},{"name":"yjn_27","display":[{"name":"yjn_5","transform":{"x":-64.45,"y":3.16}},{"name":"yjn_6","transform":{"x":-39.08,"y":-0.28}},{"name":"yjn_7","transform":{"x":-39.03,"y":0.58}}]},{"name":"yjn_35","display":[{"name":"yjn_5","transform":{"x":-64.45,"y":3.16}},{"name":"yjn_6","transform":{"x":-39.08,"y":-0.28}},{"name":"yjn_7","transform":{"x":-39.03,"y":0.58}}]},{"name":"yjn_12","display":[{"name":"yjn_5","transform":{"x":-64.45,"y":3.16}},{"name":"yjn_6","transform":{"x":-39.08,"y":-0.28}},{"name":"yjn_7","transform":{"x":-39.03,"y":0.58}}]},{"name":"yjn_15","display":[{"name":"yjn_8","transform":{"x":-0.14,"y":0.78,"scX":0.664,"scY":0.664}}]},{"name":"yjn_14","display":[{"name":"yjn_8","transform":{"x":-0.14,"y":0.78,"scX":0.664,"scY":0.664}}]},{"name":"yjn_34","display":[{"name":"yjn_5","transform":{"x":-64.45,"y":3.16}},{"name":"yjn_6","transform":{"x":-39.08,"y":-0.28}},{"name":"yjn_7","transform":{"x":-39.03,"y":0.58}}]},{"name":"yjn_31","display":[{"name":"yjn_5","transform":{"x":-64.45,"y":3.16}},{"name":"yjn_6","transform":{"x":-39.08,"y":-0.28}},{"name":"yjn_7","transform":{"x":-39.03,"y":0.58}}]},{"name":"yjn_11","display":[{"name":"yjn_5","transform":{"x":-64.45,"y":3.16}},{"name":"yjn_6","transform":{"x":-39.08,"y":-0.28}},{"name":"yjn_7","transform":{"x":-39.03,"y":0.58}}]},{"name":"yjn_29","display":[{"name":"yjn_5","transform":{"x":-64.45,"y":3.16}},{"name":"yjn_6","transform":{"x":-39.08,"y":-0.28}},{"name":"yjn_7","transform":{"x":-39.03,"y":0.58}}]},{"name":"yjn_32","display":[{"name":"yjn_5","transform":{"x":-64.45,"y":3.16}},{"name":"yjn_6","transform":{"x":-39.08,"y":-0.28}},{"name":"yjn_7","transform":{"x":-39.03,"y":0.58}}]},{"name":"yjn_8","display":[{"name":"yjn_8","transform":{"x":-0.14,"y":0.78,"scX":0.664,"scY":0.664}}]},{"name":"yjn_33","display":[{"name":"yjn_5","transform":{"x":-64.45,"y":3.16}},{"name":"yjn_6","transform":{"x":-39.08,"y":-0.28}},{"name":"yjn_7","transform":{"x":-39.03,"y":0.58}}]},{"name":"yjn_30","display":[{"name":"yjn_5","transform":{"x":-64.45,"y":3.16}},{"name":"yjn_6","transform":{"x":-39.08,"y":-0.28}},{"name":"yjn_7","transform":{"x":-39.03,"y":0.58}}]},{"name":"yjn_10","display":[{"name":"yjn_5","transform":{"x":-64.45,"y":3.16}},{"name":"yjn_6","transform":{"x":-39.08,"y":-0.28}},{"name":"yjn_7","transform":{"x":-39.03,"y":0.58}}]},{"name":"yjn_28","display":[{"name":"yjn_5","transform":{"x":-64.45,"y":3.16}},{"name":"yjn_6","transform":{"x":-39.08,"y":-0.28}},{"name":"yjn_7","transform":{"x":-39.03,"y":0.58}}]},{"name":"yjn_26","display":[{"name":"yjn_5","transform":{"x":-64.45,"y":3.16}},{"name":"yjn_6","transform":{"x":-39.08,"y":-0.28}},{"name":"yjn_7","transform":{"x":-39.03,"y":0.58}}]},{"name":"yjn_24","display":[{"name":"yjn_5","transform":{"x":-64.45,"y":3.16}},{"name":"yjn_6","transform":{"x":-39.08,"y":-0.28}},{"name":"yjn_7","transform":{"x":-39.03,"y":0.58}}]},{"name":"yjn_23","display":[{"name":"yjn_5","transform":{"x":-64.45,"y":3.16}},{"name":"yjn_6","transform":{"x":-39.08,"y":-0.28}},{"name":"yjn_7","transform":{"x":-39.03,"y":0.58}}]},{"name":"yjn_21","display":[{"name":"yjn_5","transform":{"x":-64.45,"y":3.16}},{"name":"yjn_6","transform":{"x":-39.08,"y":-0.28}},{"name":"yjn_7","transform":{"x":-39.03,"y":0.58}}]},{"name":"yjn_13","display":[{"name":"yjn_8","transform":{"x":-0.14,"y":0.78,"scX":0.664,"scY":0.664}}]},{"name":"yjn_9","display":[{"name":"yjn_5","transform":{"x":-64.45,"y":3.16}},{"name":"yjn_6","transform":{"x":-39.08,"y":-0.28}},{"name":"yjn_7","transform":{"x":-39.03,"y":0.58}}]},{"name":"yjn_22","display":[{"name":"yjn_5","transform":{"x":-64.45,"y":3.16}},{"name":"yjn_6","transform":{"x":-39.08,"y":-0.28}},{"name":"yjn_7","transform":{"x":-39.03,"y":0.58}}]}]}],"animation":[{"duration":10,"name":"attack","bone":[{"name":"t_4","translateFrame":[{"duration":6,"tweenEasing":0,"x":-43.34,"y":157},{"duration":4,"x":-42.09,"y":126.79}]},{"name":"t_5","translateFrame":[{"duration":6,"tweenEasing":0,"x":-26.38,"y":86.63},{"duration":4,"x":-25.14,"y":56.43}]},{"name":"y_1","translateFrame":[{"duration":10,"x":-2.78,"y":66.42}],"scaleFrame":[{"duration":10,"tweenEasing":0},{"duration":0,"x":2.17,"y":2.17}]},{"name":"y_2","translateFrame":[{"duration":10,"x":3.5,"y":71.26}],"scaleFrame":[{"duration":10,"tweenEasing":0},{"duration":0,"x":2.17,"y":2.17}]},{"name":"y_3","translateFrame":[{"duration":10,"x":2.82,"y":61.57}],"scaleFrame":[{"duration":10,"tweenEasing":0},{"duration":0,"x":2.17,"y":2.17}]},{"name":"t_3","translateFrame":[{"duration":4,"tweenEasing":0},{"duration":4,"tweenEasing":0,"x":27.96,"y":118.11},{"duration":2,"tweenEasing":0,"x":28.48,"y":105.54},{"duration":0,"x":29.14,"y":89.6}]},{"name":"t_9","translateFrame":[{"duration":6,"tweenEasing":0,"x":103.57,"y":19.14},{"duration":4,"x":70.05,"y":18.69}]},{"name":"t_10","translateFrame":[{"duration":6,"tweenEasing":0,"x":90.57,"y":-28.43},{"duration":4,"x":57.06,"y":-28.43}]},{"name":"t_8","translateFrame":[{"duration":4,"tweenEasing":0},{"duration":6,"tweenEasing":0,"x":116.96,"y":28.72},{"duration":0,"x":85.97,"y":28.72}]},{"name":"t_13","translateFrame":[{"duration":4,"tweenEasing":0},{"duration":6,"tweenEasing":0,"x":20.03,"y":-46.74},{"duration":0,"x":20.03,"y":-20.03}]},{"name":"t_14","translateFrame":[{"duration":6,"tweenEasing":0,"x":-40.92,"y":-93.8},{"duration":4,"x":-40.92,"y":-52.36}]},{"name":"t_15","translateFrame":[{"duration":6,"tweenEasing":0,"x":-24.77,"y":-170.59},{"duration":4,"x":-24.77,"y":-129.15}]},{"name":"t_18","translateFrame":[{"duration":4,"tweenEasing":0},{"duration":6,"tweenEasing":0,"x":-136.26,"y":41.89},{"duration":0,"x":-102.83,"y":41.89}]},{"name":"t_19","translateFrame":[{"duration":6,"tweenEasing":0,"x":-230.06,"y":19.7},{"duration":4,"x":-197.21,"y":19.7}]},{"name":"t_20","translateFrame":[{"duration":6,"tweenEasing":0,"x":-241.31,"y":-27.06},{"duration":4,"x":-208.47,"y":-26.5}]},{"name":"y_4","translateFrame":[{"duration":10,"x":-1.42,"y":75.54}],"scaleFrame":[{"duration":10,"tweenEasing":0},{"duration":0,"x":2.04,"y":2.04}]}],"slot":[{"name":"yjn_7","displayFrame":[{"duration":4,"value":-1},{"duration":2},{"duration":2,"value":1},{"duration":2,"value":2},{"duration":0,"value":-1}]},{"name":"yjn_8","colorFrame":[{"duration":5,"tweenEasing":0},{"duration":5,"tweenEasing":0,"value":{"aM":56}},{"duration":0,"value":{"aM":0}}]},{"name":"yjn_9","displayFrame":[{"duration":2},{"duration":2,"value":1},{"duration":2,"value":2},{"duration":4,"value":-1}]},{"name":"yjn_10","displayFrame":[{"duration":2,"value":1},{"duration":2,"value":2},{"duration":2},{"duration":4,"value":-1}]},{"name":"yjn_13","colorFrame":[{"duration":5,"tweenEasing":0},{"duration":5,"tweenEasing":0,"value":{"aM":56}},{"duration":0,"value":{"aM":0}}]},{"name":"yjn_14","colorFrame":[{"duration":5,"tweenEasing":0},{"duration":5,"tweenEasing":0,"value":{"aM":56}},{"duration":0,"value":{"aM":0}}]},{"name":"yjn_15","colorFrame":[{"duration":5,"tweenEasing":0},{"duration":5,"tweenEasing":0,"value":{"aM":56}},{"duration":0,"value":{"aM":0}}]},{"name":"yjn_21","displayFrame":[{"duration":4,"value":-1},{"duration":2},{"duration":2,"value":1},{"duration":2,"value":2},{"duration":0,"value":-1}]},{"name":"yjn_22","displayFrame":[{"duration":2,"value":1},{"duration":2,"value":2},{"duration":2},{"duration":4,"value":-1}]},{"name":"yjn_23","displayFrame":[{"duration":2},{"duration":2,"value":1},{"duration":2,"value":2},{"duration":4,"value":-1}]},{"name":"yjn_26","displayFrame":[{"duration":4,"value":-1},{"duration":2},{"duration":2,"value":1},{"duration":2,"value":2},{"duration":0,"value":-1}]},{"name":"yjn_27","displayFrame":[{"duration":2,"value":1},{"duration":2,"value":2},{"duration":2},{"duration":4,"value":-1}]},{"name":"yjn_28","displayFrame":[{"duration":2},{"duration":2,"value":1},{"duration":2,"value":2},{"duration":4,"value":-1}]},{"name":"yjn_31","displayFrame":[{"duration":4,"value":-1},{"duration":2},{"duration":2,"value":1},{"duration":2,"value":2},{"duration":0,"value":-1}]},{"name":"yjn_32","displayFrame":[{"duration":2},{"duration":2,"value":1},{"duration":2,"value":2},{"duration":4,"value":-1}]},{"name":"yjn_33","displayFrame":[{"duration":2,"value":1},{"duration":2,"value":2},{"duration":2},{"duration":4,"value":-1}]}]},{"duration":14,"name":"attack2","bone":[{"name":"t_4","translateFrame":[{"duration":6,"tweenEasing":0,"x":-43.34,"y":157},{"duration":8,"x":-42.09,"y":126.79}]},{"name":"t_5","translateFrame":[{"duration":6,"tweenEasing":0,"x":-26.38,"y":86.63},{"duration":8,"x":-25.14,"y":56.43}]},{"name":"y_1","translateFrame":[{"duration":14,"x":-2.78,"y":66.42}],"scaleFrame":[{"duration":10,"tweenEasing":0},{"duration":4,"x":2.17,"y":2.17}]},{"name":"y_2","translateFrame":[{"duration":14,"x":3.5,"y":71.26}],"scaleFrame":[{"duration":10,"tweenEasing":0},{"duration":4,"x":2.17,"y":2.17}]},{"name":"y_3","translateFrame":[{"duration":14,"x":2.82,"y":61.57}],"scaleFrame":[{"duration":10,"tweenEasing":0},{"duration":4,"x":2.17,"y":2.17}]},{"name":"t_3","translateFrame":[{"duration":4,"tweenEasing":0},{"duration":6,"tweenEasing":0,"x":27.96,"y":118.11},{"duration":4,"x":29.14,"y":89.6}]},{"name":"t_9","translateFrame":[{"duration":6,"tweenEasing":0,"x":103.57,"y":19.14},{"duration":8,"x":70.05,"y":18.69}]},{"name":"t_10","translateFrame":[{"duration":6,"tweenEasing":0,"x":90.57,"y":-28.43},{"duration":8,"x":57.06,"y":-28.43}]},{"name":"t_8","translateFrame":[{"duration":4,"tweenEasing":0},{"duration":6,"tweenEasing":0,"x":116.96,"y":28.72},{"duration":4,"x":85.97,"y":28.72}]},{"name":"t_13","translateFrame":[{"duration":4,"tweenEasing":0},{"duration":6,"tweenEasing":0,"x":20.03,"y":-46.74},{"duration":4,"x":20.03,"y":-20.03}]},{"name":"t_14","translateFrame":[{"duration":6,"tweenEasing":0,"x":-40.92,"y":-93.8},{"duration":8,"x":-40.92,"y":-52.36}]},{"name":"t_15","translateFrame":[{"duration":6,"tweenEasing":0,"x":-24.77,"y":-170.59},{"duration":8,"x":-24.77,"y":-129.15}]},{"name":"t_18","translateFrame":[{"duration":4,"tweenEasing":0},{"duration":6,"tweenEasing":0,"x":-136.26,"y":41.89},{"duration":4,"x":-102.83,"y":41.89}]},{"name":"t_19","translateFrame":[{"duration":6,"tweenEasing":0,"x":-230.06,"y":19.7},{"duration":8,"x":-197.21,"y":19.7}]},{"name":"t_20","translateFrame":[{"duration":6,"tweenEasing":0,"x":-241.31,"y":-27.06},{"duration":8,"x":-208.47,"y":-26.5}]},{"name":"y_4","translateFrame":[{"duration":14,"x":-1.42,"y":75.54}],"scaleFrame":[{"duration":10,"tweenEasing":0},{"duration":4,"x":2.04,"y":2.04}]},{"name":"t_6","translateFrame":[{"duration":8,"tweenEasing":0},{"duration":6,"tweenEasing":0,"x":2.75,"y":116.94},{"duration":0,"x":4.04,"y":85.7}]},{"name":"t_7","translateFrame":[{"duration":8,"tweenEasing":0},{"duration":6,"tweenEasing":0,"x":-13.8,"y":137.26},{"duration":0,"x":-11.28,"y":76.16}]},{"name":"t_12","translateFrame":[{"duration":8,"tweenEasing":0},{"duration":6,"tweenEasing":0,"x":93.75,"y":-9},{"duration":0,"x":58.5,"y":-9}]},{"name":"t_11","translateFrame":[{"duration":8,"tweenEasing":0},{"duration":6,"tweenEasing":0,"x":126.48,"y":5.55},{"duration":0,"x":63.55,"y":5.55}]},{"name":"t_17","translateFrame":[{"duration":8,"tweenEasing":0},{"duration":6,"tweenEasing":0,"x":-7.19,"y":-95.87},{"duration":0,"x":-7.19,"y":-64.3}]},{"name":"t_16","translateFrame":[{"duration":8,"tweenEasing":0},{"duration":6,"tweenEasing":0,"x":7.05,"y":-112.89},{"duration":0,"x":7.05,"y":-58.01}]},{"name":"t_22","translateFrame":[{"duration":8,"tweenEasing":0},{"duration":6,"tweenEasing":0,"x":-238.75,"y":9.69},{"duration":0,"x":-202.08,"y":9.69}]},{"name":"t_21","translateFrame":[{"duration":8,"tweenEasing":0},{"duration":6,"tweenEasing":0,"x":-227.92,"y":-6.47},{"duration":0,"x":-173.03,"y":-6.47}]}],"slot":[{"name":"yjn_7","displayFrame":[{"duration":4,"value":-1},{"duration":2},{"duration":2,"value":1},{"duration":2,"value":2},{"duration":4,"value":-1}]},{"name":"yjn_8","colorFrame":[{"duration":5,"tweenEasing":0},{"duration":5,"tweenEasing":0,"value":{"aM":56}},{"duration":4,"value":{"aM":0}}]},{"name":"yjn_9","displayFrame":[{"duration":2},{"duration":2,"value":1},{"duration":2,"value":2},{"duration":8,"value":-1}]},{"name":"yjn_10","displayFrame":[{"duration":2,"value":1},{"duration":2,"value":2},{"duration":2},{"duration":8,"value":-1}]},{"name":"yjn_11","displayFrame":[{"duration":8,"value":-1},{"duration":2},{"duration":2,"value":1},{"duration":2,"value":2},{"duration":0,"value":-1}]},{"name":"yjn_12","displayFrame":[{"duration":8,"value":-1},{"duration":2,"value":1},{"duration":2,"value":2},{"duration":2},{"duration":0,"value":-1}]},{"name":"yjn_13","colorFrame":[{"duration":5,"tweenEasing":0},{"duration":5,"tweenEasing":0,"value":{"aM":56}},{"duration":4,"value":{"aM":0}}]},{"name":"yjn_14","colorFrame":[{"duration":5,"tweenEasing":0},{"duration":5,"tweenEasing":0,"value":{"aM":56}},{"duration":4,"value":{"aM":0}}]},{"name":"yjn_15","colorFrame":[{"duration":5,"tweenEasing":0},{"duration":5,"tweenEasing":0,"value":{"aM":56}},{"duration":4,"value":{"aM":0}}]},{"name":"yjn_21","displayFrame":[{"duration":4,"value":-1},{"duration":2},{"duration":2,"value":1},{"duration":2,"value":2},{"duration":4,"value":-1}]},{"name":"yjn_22","displayFrame":[{"duration":2,"value":1},{"duration":2,"value":2},{"duration":2},{"duration":8,"value":-1}]},{"name":"yjn_23","displayFrame":[{"duration":2},{"duration":2,"value":1},{"duration":2,"value":2},{"duration":8,"value":-1}]},{"name":"yjn_24","displayFrame":[{"duration":8,"value":-1},{"duration":2,"value":1},{"duration":2,"value":2},{"duration":2},{"duration":0,"value":-1}]},{"name":"yjn_25","displayFrame":[{"duration":8,"value":-1},{"duration":2},{"duration":2,"value":1},{"duration":2,"value":2},{"duration":0,"value":-1}]},{"name":"yjn_26","displayFrame":[{"duration":4,"value":-1},{"duration":2},{"duration":2,"value":1},{"duration":2,"value":2},{"duration":4,"value":-1}]},{"name":"yjn_27","displayFrame":[{"duration":2,"value":1},{"duration":2,"value":2},{"duration":2},{"duration":8,"value":-1}]},{"name":"yjn_28","displayFrame":[{"duration":2},{"duration":2,"value":1},{"duration":2,"value":2},{"duration":8,"value":-1}]},{"name":"yjn_29","displayFrame":[{"duration":8,"value":-1},{"duration":2,"value":1},{"duration":2,"value":2},{"duration":2},{"duration":0,"value":-1}]},{"name":"yjn_30","displayFrame":[{"duration":8,"value":-1},{"duration":2},{"duration":2,"value":1},{"duration":2,"value":2},{"duration":0,"value":-1}]},{"name":"yjn_31","displayFrame":[{"duration":4,"value":-1},{"duration":2},{"duration":2,"value":1},{"duration":2,"value":2},{"duration":4,"value":-1}]},{"name":"yjn_32","displayFrame":[{"duration":2},{"duration":2,"value":1},{"duration":2,"value":2},{"duration":8,"value":-1}]},{"name":"yjn_33","displayFrame":[{"duration":2,"value":1},{"duration":2,"value":2},{"duration":2},{"duration":8,"value":-1}]},{"name":"yjn_34","displayFrame":[{"duration":8,"value":-1},{"duration":2,"value":1},{"duration":2,"value":2},{"duration":2},{"duration":0,"value":-1}]},{"name":"yjn_35","displayFrame":[{"duration":8,"value":-1},{"duration":2},{"duration":2,"value":1},{"duration":2,"value":2},{"duration":0,"value":-1}]}]}],"defaultActions":[{"gotoAndPlay":"attack"}]}]}