{"frameRate":30,"name":"sgzd_ske","version":"5.5","compatibleVersion":"5.5","armature":[{"type":"Armature","frameRate":30,"name":"armatureName","aabb":{"x":-270.01,"y":-118.99,"width":560.29,"height":241.76},"bone":[{"name":"root"},{"name":"bone","parent":"root"},{"name":"bone2","parent":"root"},{"name":"bone3","parent":"bone2","transform":{"x":-6.38,"y":-8.96}},{"name":"bone4","parent":"bone2","transform":{"x":11.96,"y":14.04}},{"name":"bone5","parent":"bone2"}],"slot":[{"name":"sgzd_1","parent":"bone2"},{"name":"sgzd_2","parent":"bone4"},{"name":"sgzd_10","parent":"bone"},{"name":"sgzd_11","parent":"bone"},{"name":"sgzd_6","parent":"bone"},{"name":"sgzd_7","parent":"bone"},{"name":"sgzd_8","parent":"bone"},{"name":"sgzd_9","parent":"bone"},{"name":"sgzd_3","parent":"bone3"},{"name":"sgzd_12","parent":"bone5"},{"name":"sgzd_4","parent":"bone2"},{"name":"sgzd_5","parent":"bone2"}],"skin":[{"slot":[{"name":"sgzd_8","display":[{"name":"sgzd_8","transform":{"x":-46.97,"y":-37.32}}]},{"name":"sgzd_3","display":[{"name":"sgzd_3","transform":{"x":2.95,"y":5.12}},{"name":"sgzd_14","transform":{"x":2.95,"y":5.12}}]},{"name":"sgzd_2","display":[{"name":"sgzd_2","transform":{"x":-5.87,"y":-5.14}},{"name":"sgzd_13","transform":{"x":-5.87,"y":-5.13}}]},{"name":"sgzd_4","display":[{"name":"sgzd_4"}]},{"name":"sgzd_11","display":[{"name":"sgzd_11","transform":{"x":-39.44,"y":53.82}}]},{"name":"sgzd_1","display":[{"name":"sgzd_1"}]},{"name":"sgzd_7","display":[{"name":"sgzd_7","transform":{"x":33.14,"y":-60.99}}]},{"name":"sgzd_9","display":[{"name":"sgzd_9","transform":{"x":93.43,"y":26.66}}]},{"name":"sgzd_12","display":[{"name":"sgzd_12"}]},{"name":"sgzd_10","display":[{"name":"sgzd_10","transform":{"x":144.78,"y":-54.54}}]},{"name":"sgzd_5","display":[{"name":"sgzd_5"}]},{"name":"sgzd_6","display":[{"name":"sgzd_6","transform":{"x":-132.01,"y":57.77}}]}]}],"animation":[{"duration":20,"name":"sgzd_1","slot":[{"name":"sgzd_1","displayFrame":[{"duration":20,"value":-1}]},{"name":"sgzd_2","displayFrame":[{"duration":20,"value":-1}]},{"name":"sgzd_3","displayFrame":[{"duration":20,"value":-1}]},{"name":"sgzd_4","displayFrame":[{"duration":20,"value":-1}]},{"name":"sgzd_5","colorFrame":[{"duration":10,"tweenEasing":0},{"duration":10,"tweenEasing":0,"value":{"aM":32}},{"duration":0}]},{"name":"sgzd_6","displayFrame":[{"duration":20,"value":-1}]},{"name":"sgzd_7","displayFrame":[{"duration":20,"value":-1}]},{"name":"sgzd_8","displayFrame":[{"duration":20,"value":-1}]},{"name":"sgzd_9","displayFrame":[{"duration":20,"value":-1}]},{"name":"sgzd_10","displayFrame":[{"duration":20,"value":-1}]},{"name":"sgzd_11","displayFrame":[{"duration":20,"value":-1}]},{"name":"sgzd_12","displayFrame":[{"duration":20,"value":-1}]}]},{"duration":7,"name":"sgzd_2","slot":[{"name":"sgzd_1","displayFrame":[{"duration":7,"value":-1}]},{"name":"sgzd_2","displayFrame":[{"duration":7,"value":-1}]},{"name":"sgzd_3","displayFrame":[{"duration":7,"value":-1}]},{"name":"sgzd_4","colorFrame":[{"duration":7,"tweenEasing":0,"value":{"aM":0}},{"duration":0}]},{"name":"sgzd_5","colorFrame":[{"duration":7,"value":{"aM":49}}]},{"name":"sgzd_6","displayFrame":[{"duration":7,"value":-1}]},{"name":"sgzd_7","displayFrame":[{"duration":7,"value":-1}]},{"name":"sgzd_8","displayFrame":[{"duration":7,"value":-1}]},{"name":"sgzd_9","displayFrame":[{"duration":7,"value":-1}]},{"name":"sgzd_10","displayFrame":[{"duration":7,"value":-1}]},{"name":"sgzd_11","displayFrame":[{"duration":7,"value":-1}]},{"name":"sgzd_12","displayFrame":[{"duration":7,"value":-1}]}]},{"duration":13,"name":"sgzd_3","bone":[{"name":"bone2","translateFrame":[{"duration":2,"tweenEasing":0,"x":-2.23,"y":-6.32},{"duration":2,"tweenEasing":0,"x":-7.81,"y":-2.23},{"duration":2,"tweenEasing":0,"x":-2.23,"y":-6.32},{"duration":7,"x":-7.81,"y":-2.23}]},{"name":"bone","rotateFrame":[{"duration":10,"tweenEasing":0,"rotate":12.89},{"duration":3}],"scaleFrame":[{"duration":10,"tweenEasing":0,"x":0.1,"y":0.1},{"duration":3}]},{"name":"bone3","translateFrame":[{"duration":8,"tweenEasing":0,"x":-2.33},{"duration":5,"x":-9.32}]},{"name":"bone4","translateFrame":[{"duration":11,"tweenEasing":0,"x":2.33},{"duration":2,"x":14.65}]},{"name":"bone5","translateFrame":[{"duration":13,"x":3.47,"y":5.4}],"scaleFrame":[{"duration":13,"x":0.68,"y":0.68}]}],"slot":[{"name":"sgzd_1","displayFrame":[{"duration":13,"value":-1}]},{"name":"sgzd_2","displayFrame":[{"duration":7},{"duration":6,"value":1}],"colorFrame":[{"duration":7},{"duration":2,"tweenEasing":0},{"duration":4,"value":{"aM":0}}]},{"name":"sgzd_3","displayFrame":[{"duration":7},{"duration":6,"value":1}],"colorFrame":[{"duration":7},{"duration":2,"tweenEasing":0},{"duration":4,"value":{"aM":0}}]}]}],"defaultActions":[{"gotoAndPlay":"sgzd_1"}]}]}