{"frameRate":30,"name":"ywcz_1","version":"5.5","compatibleVersion":"5.5","armature":[{"type":"Armature","frameRate":30,"name":"armatureName","bone":[{"name":"root"},{"name":"bone","parent":"root"},{"name":"bone2","parent":"root"}],"slot":[{"displayIndex":-1,"name":"llll_1","parent":"root"},{"displayIndex":-1,"name":"llll_5","parent":"bone"},{"displayIndex":-1,"name":"llll_6","parent":"bone2"}],"skin":[{"slot":[{"name":"llll_6","display":[{"name":"llll_6"}]},{"name":"llll_5","display":[{"name":"llll_5"}]},{"name":"llll_1","display":[{"name":"llll_1"},{"name":"llll_2"},{"name":"llll_3"},{"name":"llll_4"}]}]}],"animation":[{"duration":14,"name":"attack","bone":[{"name":"bone","scaleFrame":[{"duration":8,"tweenEasing":0},{"duration":4,"tweenEasing":0},{"duration":2,"x":1.17,"y":1.17}]},{"name":"bone2","scaleFrame":[{"duration":10,"tweenEasing":0},{"duration":4,"tweenEasing":0},{"duration":0,"x":1.08,"y":1.08}]}],"slot":[{"name":"llll_1","displayFrame":[{"duration":2},{"duration":2,"value":1},{"duration":2,"value":2},{"duration":2,"value":3},{"duration":6,"value":-1}]},{"name":"llll_5","displayFrame":[{"duration":8,"value":-1},{"duration":6}],"colorFrame":[{"duration":8,"tweenEasing":0},{"duration":4,"tweenEasing":0},{"duration":2,"value":{"aM":0}}]},{"name":"llll_6","displayFrame":[{"duration":10,"value":-1},{"duration":4}],"colorFrame":[{"duration":10,"tweenEasing":0},{"duration":4,"tweenEasing":0},{"duration":0,"value":{"aM":0}}]}]}],"defaultActions":[{"gotoAndPlay":"attack"}]}]}