{"frameRate":30,"name":"xj","version":"5.5","compatibleVersion":"5.5","armature":[{"type":"Armature","frameRate":30,"name":"armatureName","bone":[{"name":"root"},{"name":"a1","parent":"root","transform":{"x":-150.46,"y":-33.5}},{"name":"j2","parent":"root","transform":{"x":-28.75,"y":46.74}},{"name":"j2_2","parent":"root","transform":{"x":-28.9,"y":46.74}},{"name":"j_1","parent":"root","transform":{"x":-0.3,"y":38.32}},{"name":"j_1_1","parent":"root","transform":{"x":0.04,"y":38.67}},{"name":"j_3","parent":"root","transform":{"x":41.71,"y":38.95}},{"name":"j_3_3","parent":"root","transform":{"x":41.84,"y":39.2}},{"name":"t_1","parent":"root","transform":{"x":-0.79,"y":20.91}},{"name":"t_2","parent":"root","transform":{"x":-0.79,"y":20.91}},{"name":"y_1","parent":"root","transform":{"x":-0.66,"y":23.89}},{"name":"y_1_1","parent":"root","transform":{"x":-0.66,"y":23.89}},{"name":"y_2","parent":"root","transform":{"x":-0.66,"y":23.89}},{"name":"y_2_2","parent":"root","transform":{"x":-0.66,"y":23.89}},{"name":"bone10","parent":"a1","transform":{"x":-51.01,"y":-109.35,"scX":0.5,"scY":0.5}},{"name":"bone11","parent":"a1","transform":{"x":-94.34,"y":-86.44,"scX":0.5,"scY":0.5}},{"name":"bone4","parent":"a1","transform":{"x":-83.03,"y":-153.61}},{"name":"bone5","parent":"a1","transform":{"x":-135.08,"y":-120.76}},{"name":"bone6","parent":"a1","transform":{"x":-165.85,"y":-66.08}},{"name":"bone7","parent":"a1","transform":{"x":-168.36,"y":-0.08}},{"name":"bone8","parent":"a1","transform":{"x":-9.68,"y":-133.75,"scX":0.5,"scY":0.5}},{"name":"bone9","parent":"a1","transform":{"x":3.76,"y":-97.4,"scX":0.5,"scY":0.5}}],"slot":[{"displayIndex":-1,"name":"xxxx_1","parent":"bone4"},{"displayIndex":-1,"name":"xxxx_7","parent":"bone5"},{"displayIndex":-1,"name":"xxxx_8","parent":"bone6"},{"displayIndex":-1,"name":"xxxx_9","parent":"bone7"},{"displayIndex":-1,"name":"xxxx_10","parent":"bone8"},{"displayIndex":-1,"name":"xxxx_11","parent":"bone9"},{"displayIndex":-1,"name":"xxxx_12","parent":"bone10"},{"displayIndex":-1,"name":"xxxx_13","parent":"bone11"},{"displayIndex":-1,"name":"jl_2","parent":"j_3"},{"displayIndex":-1,"name":"jl_6","parent":"j_3_3"},{"displayIndex":-1,"name":"jl_1","parent":"j_1"},{"displayIndex":-1,"name":"jl_5","parent":"j_1_1"},{"displayIndex":-1,"name":"jl_3","parent":"j2"},{"displayIndex":-1,"name":"jl_4","parent":"j2_2"},{"displayIndex":-1,"name":"tl_1","parent":"t_1"},{"displayIndex":-1,"name":"tl_2","parent":"t_2"},{"displayIndex":-1,"name":"yl_3","parent":"y_2"},{"displayIndex":-1,"name":"yl_4","parent":"y_2_2"},{"displayIndex":-1,"name":"yl_1","parent":"y_1"},{"displayIndex":-1,"name":"yl_2","parent":"y_1_1"}],"skin":[{"slot":[{"name":"jl_6","display":[{"name":"jl_1","transform":{"x":0.64,"y":-37.08}}]},{"name":"yl_4","display":[{"name":"yl_1","transform":{"x":0.58,"y":-30.71}}]},{"name":"yl_3","display":[{"name":"yl_1","transform":{"x":0.58,"y":-30.71}}]},{"name":"jl_2","display":[{"name":"jl_1","transform":{"x":0.76,"y":-36.83}}]},{"name":"xxxx_13","display":[{"name":"xxxx_1","transform":{"x":0.82,"y":-0.46}},{"name":"xxxx_2","transform":{"x":-1.45,"y":-0.25}},{"name":"xxxx_3","transform":{"x":0.49,"y":-0.49}}]},{"name":"yl_2","display":[{"name":"yl_1","transform":{"x":0.58,"y":-30.71}}]},{"name":"tl_1","display":[{"name":"tl_1","transform":{"x":0.76,"y":-30.48}}]},{"name":"xxxx_11","display":[{"name":"xxxx_1","transform":{"x":0.82,"y":-0.46}},{"name":"xxxx_2","transform":{"x":2.84,"y":-1.48}},{"name":"xxxx_3","transform":{"x":4.11,"y":-3.66}}]},{"name":"jl_4","display":[{"name":"jl_1","transform":{"x":0.36,"y":-36.65}}]},{"name":"xxxx_1","display":[{"name":"xxxx_1","transform":{"x":0.82,"y":-0.46}},{"name":"xxxx_2","transform":{"x":1.06,"y":-1.34}},{"name":"xxxx_3","transform":{"x":0.15,"y":-1.19}}]},{"name":"xxxx_9","display":[{"name":"xxxx_1","transform":{"x":0.82,"y":-0.46}},{"name":"xxxx_2","transform":{"x":-0.18,"y":-1.43}},{"name":"xxxx_3","transform":{"x":-0.22,"y":-0.54}}]},{"name":"jl_1","display":[{"name":"jl_1","transform":{"x":0.22,"y":-36.65}}]},{"name":"xxxx_7","display":[{"name":"xxxx_1","transform":{"x":0.82,"y":-0.46}},{"name":"xxxx_2","transform":{"x":0.39,"y":-2.25}},{"name":"xxxx_3","transform":{"x":-0.68,"y":-3.41}}]},{"name":"jl_3","display":[{"name":"jl_1","transform":{"x":0.21,"y":-36.65}}]},{"name":"tl_2","display":[{"name":"tl_1","transform":{"x":0.76,"y":-30.48}}]},{"name":"xxxx_12","display":[{"name":"xxxx_1","transform":{"x":0.82,"y":-0.46}},{"name":"xxxx_2","transform":{"x":-1.65,"y":-0.18}},{"name":"xxxx_3","transform":{"x":-2.52,"y":0.41}}]},{"name":"yl_1","display":[{"name":"yl_1","transform":{"x":0.58,"y":-30.71}}]},{"name":"xxxx_10","display":[{"name":"xxxx_1","transform":{"x":0.82,"y":-0.46}},{"name":"xxxx_2","transform":{"x":-0.61,"y":-2.12}},{"name":"xxxx_3","transform":{"x":0.86,"y":-3.71}}]},{"name":"jl_5","display":[{"name":"jl_1","transform":{"x":-0.12,"y":-37}}]},{"name":"xxxx_8","display":[{"name":"xxxx_1","transform":{"x":0.82,"y":-0.46}},{"name":"xxxx_2","transform":{"x":0.79,"y":0.08}},{"name":"xxxx_3","transform":{"x":0.53,"y":1.51}}]}]}],"animation":[{"duration":50,"name":"attack_j_1","bone":[{"name":"bone4","translateFrame":[{"duration":5,"tweenEasing":0},{"duration":10,"tweenEasing":0,"x":205.84,"y":198.75},{"duration":5,"tweenEasing":0,"x":84.65,"y":186.59},{"duration":10,"tweenEasing":0,"x":234.88,"y":188.85},{"duration":5,"tweenEasing":0,"x":125.71,"y":152.13},{"duration":10,"tweenEasing":0,"x":263.79,"y":179.21},{"duration":5,"x":138.75,"y":170.84}]},{"name":"bone5","translateFrame":[{"duration":5,"tweenEasing":0},{"duration":10,"tweenEasing":0,"x":257.79,"y":165.96},{"duration":5,"tweenEasing":0,"x":388.73,"y":156.16},{"duration":10,"tweenEasing":0,"x":286.83,"y":156.06},{"duration":5,"tweenEasing":0,"x":429.79,"y":121.69},{"duration":10,"tweenEasing":0,"x":315.75,"y":146.42},{"duration":5,"x":442.83,"y":140.41}]},{"name":"bone6","translateFrame":[{"duration":5,"tweenEasing":0},{"duration":10,"tweenEasing":0,"x":288,"y":113.1},{"duration":5,"tweenEasing":0,"x":379.23,"y":7.17},{"duration":10,"tweenEasing":0,"x":317.04,"y":103.2},{"duration":5,"tweenEasing":0,"x":420.29,"y":-27.28},{"duration":10,"tweenEasing":0,"x":345.96,"y":93.56},{"duration":5,"x":433.33,"y":-8.57}]},{"name":"bone7","translateFrame":[{"duration":5,"tweenEasing":0},{"duration":10,"tweenEasing":0,"x":291.78,"y":46.07},{"duration":5,"tweenEasing":0,"x":223.75,"y":-67.95},{"duration":10,"tweenEasing":0,"x":320.82,"y":36.17},{"duration":5,"tweenEasing":0,"x":264.81,"y":-102.41},{"duration":10,"tweenEasing":0,"x":349.74,"y":26.53},{"duration":5,"x":277.85,"y":-83.7}]},{"name":"bone8","translateFrame":[{"duration":10,"tweenEasing":0},{"duration":10,"tweenEasing":0,"x":134.99,"y":178.44},{"duration":5,"tweenEasing":0,"x":209.14,"y":63.27},{"duration":10,"tweenEasing":0,"x":165.79,"y":166.71},{"duration":5,"tweenEasing":0,"x":240.67,"y":61.8},{"duration":10,"tweenEasing":0,"x":190.74,"y":166.71},{"duration":0,"x":263.35,"y":61.8}]},{"name":"bone9","translateFrame":[{"duration":10,"tweenEasing":0},{"duration":10,"tweenEasing":0,"x":119.73,"y":140.28},{"duration":5,"tweenEasing":0,"x":118.55,"y":8.96},{"duration":10,"tweenEasing":0,"x":150.52,"y":128.55},{"duration":5,"tweenEasing":0,"x":150.07,"y":7.49},{"duration":10,"tweenEasing":0,"x":175.47,"y":128.55},{"duration":0,"x":172.75,"y":7.49}]},{"name":"bone10","translateFrame":[{"duration":10,"tweenEasing":0},{"duration":10,"tweenEasing":0,"x":174.85,"y":153.85},{"duration":5,"tweenEasing":0,"x":54.07,"y":84.44},{"duration":10,"tweenEasing":0,"x":205.64,"y":142.11},{"duration":5,"tweenEasing":0,"x":85.6,"y":82.97},{"duration":10,"tweenEasing":0,"x":230.59,"y":142.11},{"duration":0,"x":108.28,"y":82.97}]},{"name":"bone11","translateFrame":[{"duration":10,"tweenEasing":0},{"duration":10,"tweenEasing":0,"x":221.49,"y":130.95},{"duration":5,"tweenEasing":0,"x":356.04,"y":91.02},{"duration":10,"tweenEasing":0,"x":252.28,"y":119.22},{"duration":5,"tweenEasing":0,"x":387.57,"y":89.55},{"duration":10,"tweenEasing":0,"x":277.23,"y":119.22},{"duration":0,"x":410.25,"y":89.55}]},{"name":"j_1","translateFrame":[{"duration":15,"tweenEasing":0},{"duration":3,"tweenEasing":0,"x":4.12,"y":-102.55},{"duration":32,"x":4.12,"y":-4.55}]},{"name":"j2","translateFrame":[{"duration":3,"tweenEasing":0,"y":-109.14},{"duration":47,"y":-0.26}],"scaleFrame":[{"duration":50,"x":0.83,"y":0.83}]},{"name":"j2_2","translateFrame":[{"duration":5,"tweenEasing":0},{"duration":5,"tweenEasing":0,"y":-0.26},{"duration":40,"y":20.2}],"scaleFrame":[{"duration":5,"tweenEasing":0},{"duration":5,"tweenEasing":0},{"duration":40,"x":2.5,"y":2.5}]},{"name":"j_1_1","translateFrame":[{"duration":20,"tweenEasing":0},{"duration":5,"tweenEasing":0,"x":4.12,"y":-4.55},{"duration":25,"x":4.12,"y":22.16}],"scaleFrame":[{"duration":20,"tweenEasing":0},{"duration":5,"tweenEasing":0},{"duration":25,"x":2.5,"y":2.5}]},{"name":"j_3","translateFrame":[{"duration":30,"tweenEasing":0},{"duration":3,"tweenEasing":0,"x":-12.67,"y":-104.82},{"duration":17,"x":-12.67,"y":-11.23}],"scaleFrame":[{"duration":30,"tweenEasing":0},{"duration":20,"x":0.75,"y":0.75}]},{"name":"j_3_3","translateFrame":[{"duration":35,"tweenEasing":0},{"duration":5,"tweenEasing":0,"x":-12.67,"y":-11.23},{"duration":10,"x":-12.67,"y":14.24}],"scaleFrame":[{"duration":35,"tweenEasing":0},{"duration":5,"tweenEasing":0},{"duration":10,"x":2.5,"y":2.5}]}],"slot":[{"name":"jl_1","displayFrame":[{"duration":15,"value":-1},{"duration":35}],"colorFrame":[{"duration":15,"tweenEasing":0},{"duration":3,"tweenEasing":0,"value":{"aM":0}},{"duration":32}]},{"name":"jl_2","displayFrame":[{"duration":30,"value":-1},{"duration":20}],"colorFrame":[{"duration":30,"tweenEasing":0},{"duration":3,"tweenEasing":0,"value":{"aM":0}},{"duration":17}]},{"name":"jl_3","displayFrame":[{"duration":50}],"colorFrame":[{"duration":3,"tweenEasing":0,"value":{"aM":0}},{"duration":47}]},{"name":"jl_4","displayFrame":[{"duration":5,"value":-1},{"duration":45}],"colorFrame":[{"duration":7,"tweenEasing":0},{"duration":3,"tweenEasing":0},{"duration":40,"value":{"aM":0}}]},{"name":"jl_5","displayFrame":[{"duration":20,"value":-1},{"duration":30}],"colorFrame":[{"duration":22,"tweenEasing":0},{"duration":3,"tweenEasing":0},{"duration":25,"value":{"aM":0}}]},{"name":"jl_6","displayFrame":[{"duration":35,"value":-1},{"duration":15}],"colorFrame":[{"duration":37,"tweenEasing":0},{"duration":3,"tweenEasing":0},{"duration":10,"value":{"aM":0}}]},{"name":"xxxx_1","displayFrame":[{"duration":5,"value":-1},{"duration":10,"value":2},{"duration":5,"value":-1},{"duration":10,"value":2},{"duration":5,"value":-1},{"duration":10,"value":2},{"duration":5,"value":-1}],"colorFrame":[{"duration":10,"tweenEasing":0},{"duration":5,"tweenEasing":0},{"duration":5,"tweenEasing":0,"value":{"aM":0}},{"duration":5,"tweenEasing":0},{"duration":5,"tweenEasing":0},{"duration":5,"tweenEasing":0,"value":{"aM":0}},{"duration":5,"tweenEasing":0},{"duration":5,"tweenEasing":0},{"duration":5,"value":{"aM":0}}]},{"name":"xxxx_7","displayFrame":[{"duration":5,"value":-1},{"duration":10,"value":2},{"duration":5,"value":-1},{"duration":10,"value":2},{"duration":5,"value":-1},{"duration":10,"value":2},{"duration":5,"value":-1}],"colorFrame":[{"duration":10,"tweenEasing":0},{"duration":5,"tweenEasing":0},{"duration":5,"tweenEasing":0,"value":{"aM":0}},{"duration":5,"tweenEasing":0},{"duration":5,"tweenEasing":0},{"duration":5,"tweenEasing":0,"value":{"aM":0}},{"duration":5,"tweenEasing":0},{"duration":5,"tweenEasing":0},{"duration":5,"value":{"aM":0}}]},{"name":"xxxx_8","displayFrame":[{"duration":5,"value":-1},{"duration":10,"value":2},{"duration":5,"value":-1},{"duration":10,"value":2},{"duration":5,"value":-1},{"duration":10,"value":2},{"duration":5,"value":-1}],"colorFrame":[{"duration":10,"tweenEasing":0},{"duration":5,"tweenEasing":0},{"duration":5,"tweenEasing":0,"value":{"aM":0}},{"duration":5,"tweenEasing":0},{"duration":5,"tweenEasing":0},{"duration":5,"tweenEasing":0,"value":{"aM":0}},{"duration":5,"tweenEasing":0},{"duration":5,"tweenEasing":0},{"duration":5,"value":{"aM":0}}]},{"name":"xxxx_9","displayFrame":[{"duration":5,"value":-1},{"duration":10,"value":2},{"duration":5,"value":-1},{"duration":10,"value":2},{"duration":5,"value":-1},{"duration":10,"value":2},{"duration":5,"value":-1}],"colorFrame":[{"duration":10,"tweenEasing":0},{"duration":5,"tweenEasing":0},{"duration":5,"tweenEasing":0,"value":{"aM":0}},{"duration":5,"tweenEasing":0},{"duration":5,"tweenEasing":0},{"duration":5,"tweenEasing":0,"value":{"aM":0}},{"duration":5,"tweenEasing":0},{"duration":5,"tweenEasing":0},{"duration":5,"value":{"aM":0}}]},{"name":"xxxx_10","displayFrame":[{"duration":10,"value":-1},{"duration":10,"value":2},{"duration":5,"value":-1},{"duration":10,"value":2},{"duration":5,"value":-1},{"duration":10,"value":2},{"duration":0,"value":-1}],"colorFrame":[{"duration":15,"tweenEasing":0},{"duration":5,"tweenEasing":0},{"duration":5,"tweenEasing":0,"value":{"aM":0}},{"duration":5,"tweenEasing":0},{"duration":5,"tweenEasing":0},{"duration":5,"tweenEasing":0,"value":{"aM":0}},{"duration":5,"tweenEasing":0},{"duration":5,"tweenEasing":0},{"duration":0,"value":{"aM":0}}]},{"name":"xxxx_11","displayFrame":[{"duration":10,"value":-1},{"duration":10,"value":2},{"duration":5,"value":-1},{"duration":10,"value":2},{"duration":5,"value":-1},{"duration":10,"value":2},{"duration":0,"value":-1}],"colorFrame":[{"duration":15,"tweenEasing":0},{"duration":5,"tweenEasing":0},{"duration":5,"tweenEasing":0,"value":{"aM":0}},{"duration":5,"tweenEasing":0},{"duration":5,"tweenEasing":0},{"duration":5,"tweenEasing":0,"value":{"aM":0}},{"duration":5,"tweenEasing":0},{"duration":5,"tweenEasing":0},{"duration":0,"value":{"aM":0}}]},{"name":"xxxx_12","displayFrame":[{"duration":10,"value":-1},{"duration":10,"value":2},{"duration":5,"value":-1},{"duration":10,"value":2},{"duration":5,"value":-1},{"duration":10,"value":2},{"duration":0,"value":-1}],"colorFrame":[{"duration":15,"tweenEasing":0},{"duration":5,"tweenEasing":0},{"duration":5,"tweenEasing":0,"value":{"aM":0}},{"duration":5,"tweenEasing":0},{"duration":5,"tweenEasing":0},{"duration":5,"tweenEasing":0,"value":{"aM":0}},{"duration":5,"tweenEasing":0},{"duration":5,"tweenEasing":0},{"duration":0,"value":{"aM":0}}]},{"name":"xxxx_13","displayFrame":[{"duration":10,"value":-1},{"duration":10,"value":2},{"duration":5,"value":-1},{"duration":10,"value":2},{"duration":5,"value":-1},{"duration":10,"value":2},{"duration":0,"value":-1}],"colorFrame":[{"duration":15,"tweenEasing":0},{"duration":5,"tweenEasing":0},{"duration":5,"tweenEasing":0,"value":{"aM":0}},{"duration":5,"tweenEasing":0},{"duration":5,"tweenEasing":0},{"duration":5,"tweenEasing":0,"value":{"aM":0}},{"duration":5,"tweenEasing":0},{"duration":5,"tweenEasing":0},{"duration":0,"value":{"aM":0}}]}]},{"duration":50,"name":"attack_j_2","bone":[{"name":"bone4","translateFrame":[{"duration":5,"tweenEasing":0},{"duration":10,"tweenEasing":0,"x":191.5,"y":190.04},{"duration":5,"tweenEasing":0,"x":70.31,"y":186.59},{"duration":10,"tweenEasing":0,"x":234.88,"y":188.85},{"duration":5,"tweenEasing":0,"x":114.45,"y":189.22},{"duration":10,"tweenEasing":0,"x":276.08,"y":184.33},{"duration":5,"x":154.71,"y":185.61}]},{"name":"bone5","translateFrame":[{"duration":5,"tweenEasing":0},{"duration":10,"tweenEasing":0,"x":243.46,"y":157.26},{"duration":5,"tweenEasing":0,"x":374.4,"y":156.16},{"duration":10,"tweenEasing":0,"x":286.83,"y":156.06},{"duration":5,"tweenEasing":0,"x":418.53,"y":158.78},{"duration":10,"tweenEasing":0,"x":328.04,"y":151.54},{"duration":5,"x":458.79,"y":155.18}]},{"name":"bone6","translateFrame":[{"duration":5,"tweenEasing":0},{"duration":10,"tweenEasing":0,"x":273.67,"y":104.39},{"duration":5,"tweenEasing":0,"x":364.89,"y":7.17},{"duration":10,"tweenEasing":0,"x":317.04,"y":103.2},{"duration":5,"tweenEasing":0,"x":409.03,"y":9.79},{"duration":10,"tweenEasing":0,"x":358.25,"y":98.68},{"duration":5,"x":449.28,"y":6.19}]},{"name":"bone7","translateFrame":[{"duration":5,"tweenEasing":0},{"duration":10,"tweenEasing":0,"x":277.44,"y":37.37},{"duration":5,"tweenEasing":0,"x":209.41,"y":-67.95},{"duration":10,"tweenEasing":0,"x":320.82,"y":36.17},{"duration":5,"tweenEasing":0,"x":253.55,"y":-65.32},{"duration":10,"tweenEasing":0,"x":362.02,"y":31.65},{"duration":5,"x":293.81,"y":-68.92}]},{"name":"bone8","translateFrame":[{"duration":10,"tweenEasing":0},{"duration":10,"tweenEasing":0,"x":117.59,"y":169.22},{"duration":5,"tweenEasing":0,"x":192.76,"y":63.27},{"duration":10,"tweenEasing":0,"x":161.18,"y":166.71},{"duration":5,"tweenEasing":0,"x":232.48,"y":61.8},{"duration":10,"tweenEasing":0,"x":203.02,"y":166.71},{"duration":0,"x":273.59,"y":61.8}]},{"name":"bone9","translateFrame":[{"duration":10,"tweenEasing":0},{"duration":10,"tweenEasing":0,"x":102.32,"y":131.06},{"duration":5,"tweenEasing":0,"x":102.16,"y":8.96},{"duration":10,"tweenEasing":0,"x":145.92,"y":128.55},{"duration":5,"tweenEasing":0,"x":141.88,"y":7.49},{"duration":10,"tweenEasing":0,"x":187.76,"y":128.55},{"duration":0,"x":182.99,"y":7.49}]},{"name":"bone10","translateFrame":[{"duration":10,"tweenEasing":0},{"duration":10,"tweenEasing":0,"x":157.44,"y":144.63},{"duration":5,"tweenEasing":0,"x":37.69,"y":84.44},{"duration":10,"tweenEasing":0,"x":201.04,"y":142.11},{"duration":5,"tweenEasing":0,"x":77.41,"y":82.97},{"duration":10,"tweenEasing":0,"x":242.88,"y":142.11},{"duration":0,"x":118.52,"y":82.97}]},{"name":"bone11","translateFrame":[{"duration":10,"tweenEasing":0},{"duration":10,"tweenEasing":0,"x":204.08,"y":121.73},{"duration":5,"tweenEasing":0,"x":339.65,"y":91.02},{"duration":10,"tweenEasing":0,"x":247.68,"y":119.22},{"duration":5,"tweenEasing":0,"x":379.37,"y":89.55},{"duration":10,"tweenEasing":0,"x":289.52,"y":119.22},{"duration":0,"x":420.49,"y":89.55}]},{"name":"j_1","translateFrame":[{"duration":15,"tweenEasing":0},{"duration":3,"tweenEasing":0,"x":-0.43,"y":-102.55},{"duration":32,"x":-0.43,"y":-1.81}]},{"name":"j2","translateFrame":[{"duration":3,"tweenEasing":0,"x":-14.18,"y":-109.14},{"duration":47,"x":-14.18,"y":-16.18}],"scaleFrame":[{"duration":50,"x":0.83,"y":0.83}]},{"name":"j2_2","translateFrame":[{"duration":5,"tweenEasing":0},{"duration":5,"tweenEasing":0,"x":-14.18,"y":-16.53},{"duration":40,"x":-14.18,"y":12.53}],"scaleFrame":[{"duration":5,"tweenEasing":0},{"duration":5,"tweenEasing":0,"x":0.83,"y":0.83},{"duration":40,"x":2.5,"y":2.5}]},{"name":"j_1_1","translateFrame":[{"duration":20,"tweenEasing":0},{"duration":5,"tweenEasing":0,"x":-0.78,"y":-1.81},{"duration":25,"x":-0.78,"y":52.06}],"scaleFrame":[{"duration":20,"tweenEasing":0},{"duration":5,"tweenEasing":0},{"duration":25,"x":2.5,"y":2.5}]},{"name":"j_3","translateFrame":[{"duration":30,"tweenEasing":0},{"duration":3,"tweenEasing":0,"x":-0.71,"y":-104.82},{"duration":17,"x":-0.71,"y":-8.7}],"scaleFrame":[{"duration":30,"tweenEasing":0},{"duration":20,"x":0.83,"y":0.83}]},{"name":"j_3_3","translateFrame":[{"duration":35,"tweenEasing":0},{"duration":5,"tweenEasing":0,"x":-0.84,"y":-7.89},{"duration":10,"x":-0.84,"y":14.24}],"scaleFrame":[{"duration":35,"tweenEasing":0},{"duration":5,"tweenEasing":0,"x":0.83,"y":0.83},{"duration":10,"x":2.5,"y":2.5}]}],"slot":[{"name":"jl_1","displayFrame":[{"duration":15,"value":-1},{"duration":35}],"colorFrame":[{"duration":15,"tweenEasing":0},{"duration":3,"tweenEasing":0,"value":{"aM":0}},{"duration":32}]},{"name":"jl_2","displayFrame":[{"duration":30,"value":-1},{"duration":20}],"colorFrame":[{"duration":30,"tweenEasing":0},{"duration":3,"tweenEasing":0,"value":{"aM":0}},{"duration":17}]},{"name":"jl_3","displayFrame":[{"duration":50}],"colorFrame":[{"duration":3,"tweenEasing":0,"value":{"aM":0}},{"duration":47}]},{"name":"jl_4","displayFrame":[{"duration":5,"value":-1},{"duration":45}],"colorFrame":[{"duration":7,"tweenEasing":0},{"duration":3,"tweenEasing":0},{"duration":40,"value":{"aM":0}}]},{"name":"jl_5","displayFrame":[{"duration":20,"value":-1},{"duration":30}],"colorFrame":[{"duration":22,"tweenEasing":0},{"duration":3,"tweenEasing":0},{"duration":25,"value":{"aM":0}}]},{"name":"jl_6","displayFrame":[{"duration":35,"value":-1},{"duration":15}],"colorFrame":[{"duration":37,"tweenEasing":0},{"duration":3,"tweenEasing":0},{"duration":10,"value":{"aM":0}}]},{"name":"xxxx_1","displayFrame":[{"duration":5,"value":-1},{"duration":10,"value":2},{"duration":5,"value":-1},{"duration":10,"value":2},{"duration":5,"value":-1},{"duration":10,"value":2},{"duration":5,"value":-1}],"colorFrame":[{"duration":10,"tweenEasing":0},{"duration":5,"tweenEasing":0},{"duration":5,"tweenEasing":0,"value":{"aM":0}},{"duration":5,"tweenEasing":0},{"duration":5,"tweenEasing":0},{"duration":5,"tweenEasing":0,"value":{"aM":0}},{"duration":5,"tweenEasing":0},{"duration":5,"tweenEasing":0},{"duration":5,"value":{"aM":0}}]},{"name":"xxxx_7","displayFrame":[{"duration":5,"value":-1},{"duration":10,"value":2},{"duration":5,"value":-1},{"duration":10,"value":2},{"duration":5,"value":-1},{"duration":10,"value":2},{"duration":5,"value":-1}],"colorFrame":[{"duration":10,"tweenEasing":0},{"duration":5,"tweenEasing":0},{"duration":5,"tweenEasing":0,"value":{"aM":0}},{"duration":5,"tweenEasing":0},{"duration":5,"tweenEasing":0},{"duration":5,"tweenEasing":0,"value":{"aM":0}},{"duration":5,"tweenEasing":0},{"duration":5,"tweenEasing":0},{"duration":5,"value":{"aM":0}}]},{"name":"xxxx_8","displayFrame":[{"duration":5,"value":-1},{"duration":10,"value":2},{"duration":5,"value":-1},{"duration":10,"value":2},{"duration":5,"value":-1},{"duration":10,"value":2},{"duration":5,"value":-1}],"colorFrame":[{"duration":10,"tweenEasing":0},{"duration":5,"tweenEasing":0},{"duration":5,"tweenEasing":0,"value":{"aM":0}},{"duration":5,"tweenEasing":0},{"duration":5,"tweenEasing":0},{"duration":5,"tweenEasing":0,"value":{"aM":0}},{"duration":5,"tweenEasing":0},{"duration":5,"tweenEasing":0},{"duration":5,"value":{"aM":0}}]},{"name":"xxxx_9","displayFrame":[{"duration":5,"value":-1},{"duration":10,"value":2},{"duration":5,"value":-1},{"duration":10,"value":2},{"duration":5,"value":-1},{"duration":10,"value":2},{"duration":5,"value":-1}],"colorFrame":[{"duration":10,"tweenEasing":0},{"duration":5,"tweenEasing":0},{"duration":5,"tweenEasing":0,"value":{"aM":0}},{"duration":5,"tweenEasing":0},{"duration":5,"tweenEasing":0},{"duration":5,"tweenEasing":0,"value":{"aM":0}},{"duration":5,"tweenEasing":0},{"duration":5,"tweenEasing":0},{"duration":5,"value":{"aM":0}}]},{"name":"xxxx_10","displayFrame":[{"duration":10,"value":-1},{"duration":10,"value":2},{"duration":5,"value":-1},{"duration":10,"value":2},{"duration":5,"value":-1},{"duration":10,"value":2},{"duration":0,"value":-1}],"colorFrame":[{"duration":15,"tweenEasing":0},{"duration":5,"tweenEasing":0},{"duration":5,"tweenEasing":0,"value":{"aM":0}},{"duration":5,"tweenEasing":0},{"duration":5,"tweenEasing":0},{"duration":5,"tweenEasing":0,"value":{"aM":0}},{"duration":5,"tweenEasing":0},{"duration":5,"tweenEasing":0},{"duration":0,"value":{"aM":0}}]},{"name":"xxxx_11","displayFrame":[{"duration":10,"value":-1},{"duration":10,"value":2},{"duration":5,"value":-1},{"duration":10,"value":2},{"duration":5,"value":-1},{"duration":10,"value":2},{"duration":0,"value":-1}],"colorFrame":[{"duration":15,"tweenEasing":0},{"duration":5,"tweenEasing":0},{"duration":5,"tweenEasing":0,"value":{"aM":0}},{"duration":5,"tweenEasing":0},{"duration":5,"tweenEasing":0},{"duration":5,"tweenEasing":0,"value":{"aM":0}},{"duration":5,"tweenEasing":0},{"duration":5,"tweenEasing":0},{"duration":0,"value":{"aM":0}}]},{"name":"xxxx_12","displayFrame":[{"duration":10,"value":-1},{"duration":10,"value":2},{"duration":5,"value":-1},{"duration":10,"value":2},{"duration":5,"value":-1},{"duration":10,"value":2},{"duration":0,"value":-1}],"colorFrame":[{"duration":15,"tweenEasing":0},{"duration":5,"tweenEasing":0},{"duration":5,"tweenEasing":0,"value":{"aM":0}},{"duration":5,"tweenEasing":0},{"duration":5,"tweenEasing":0},{"duration":5,"tweenEasing":0,"value":{"aM":0}},{"duration":5,"tweenEasing":0},{"duration":5,"tweenEasing":0},{"duration":0,"value":{"aM":0}}]},{"name":"xxxx_13","displayFrame":[{"duration":10,"value":-1},{"duration":10,"value":2},{"duration":5,"value":-1},{"duration":10,"value":2},{"duration":5,"value":-1},{"duration":10,"value":2},{"duration":0,"value":-1}],"colorFrame":[{"duration":15,"tweenEasing":0},{"duration":5,"tweenEasing":0},{"duration":5,"tweenEasing":0,"value":{"aM":0}},{"duration":5,"tweenEasing":0},{"duration":5,"tweenEasing":0},{"duration":5,"tweenEasing":0,"value":{"aM":0}},{"duration":5,"tweenEasing":0},{"duration":5,"tweenEasing":0},{"duration":0,"value":{"aM":0}}]}]},{"duration":50,"name":"attack_j_3","bone":[{"name":"bone4","translateFrame":[{"duration":5,"tweenEasing":0},{"duration":10,"tweenEasing":0,"x":205.84,"y":198.75},{"duration":5,"tweenEasing":0,"x":84.65,"y":186.59},{"duration":10,"tweenEasing":0,"x":234.88,"y":188.85},{"duration":5,"tweenEasing":0,"x":125.71,"y":152.13},{"duration":10,"tweenEasing":0,"x":263.79,"y":179.21},{"duration":5,"x":138.75,"y":170.84}]},{"name":"bone5","translateFrame":[{"duration":5,"tweenEasing":0},{"duration":10,"tweenEasing":0,"x":257.79,"y":165.96},{"duration":5,"tweenEasing":0,"x":388.73,"y":156.16},{"duration":10,"tweenEasing":0,"x":286.83,"y":156.06},{"duration":5,"tweenEasing":0,"x":429.79,"y":121.69},{"duration":10,"tweenEasing":0,"x":315.75,"y":146.42},{"duration":5,"x":442.83,"y":140.41}]},{"name":"bone6","translateFrame":[{"duration":5,"tweenEasing":0},{"duration":10,"tweenEasing":0,"x":288,"y":113.1},{"duration":5,"tweenEasing":0,"x":379.23,"y":7.17},{"duration":10,"tweenEasing":0,"x":317.04,"y":103.2},{"duration":5,"tweenEasing":0,"x":420.29,"y":-27.28},{"duration":10,"tweenEasing":0,"x":345.96,"y":93.56},{"duration":5,"x":433.33,"y":-8.57}]},{"name":"bone7","translateFrame":[{"duration":5,"tweenEasing":0},{"duration":10,"tweenEasing":0,"x":291.78,"y":46.07},{"duration":5,"tweenEasing":0,"x":223.75,"y":-67.95},{"duration":10,"tweenEasing":0,"x":320.82,"y":36.17},{"duration":5,"tweenEasing":0,"x":264.81,"y":-102.41},{"duration":10,"tweenEasing":0,"x":349.74,"y":26.53},{"duration":5,"x":277.85,"y":-83.7}]},{"name":"bone8","translateFrame":[{"duration":10,"tweenEasing":0},{"duration":10,"tweenEasing":0,"x":134.99,"y":178.44},{"duration":5,"tweenEasing":0,"x":209.14,"y":63.27},{"duration":10,"tweenEasing":0,"x":165.79,"y":166.71},{"duration":5,"tweenEasing":0,"x":240.67,"y":61.8},{"duration":10,"tweenEasing":0,"x":190.74,"y":166.71},{"duration":0,"x":263.35,"y":61.8}]},{"name":"bone9","translateFrame":[{"duration":10,"tweenEasing":0},{"duration":10,"tweenEasing":0,"x":119.73,"y":140.28},{"duration":5,"tweenEasing":0,"x":118.55,"y":8.96},{"duration":10,"tweenEasing":0,"x":150.52,"y":128.55},{"duration":5,"tweenEasing":0,"x":150.07,"y":7.49},{"duration":10,"tweenEasing":0,"x":175.47,"y":128.55},{"duration":0,"x":172.75,"y":7.49}]},{"name":"bone10","translateFrame":[{"duration":10,"tweenEasing":0},{"duration":10,"tweenEasing":0,"x":174.85,"y":153.85},{"duration":5,"tweenEasing":0,"x":54.07,"y":84.44},{"duration":10,"tweenEasing":0,"x":205.64,"y":142.11},{"duration":5,"tweenEasing":0,"x":85.6,"y":82.97},{"duration":10,"tweenEasing":0,"x":230.59,"y":142.11},{"duration":0,"x":108.28,"y":82.97}]},{"name":"bone11","translateFrame":[{"duration":10,"tweenEasing":0},{"duration":10,"tweenEasing":0,"x":221.49,"y":130.95},{"duration":5,"tweenEasing":0,"x":356.04,"y":91.02},{"duration":10,"tweenEasing":0,"x":252.28,"y":119.22},{"duration":5,"tweenEasing":0,"x":387.57,"y":89.55},{"duration":10,"tweenEasing":0,"x":277.23,"y":119.22},{"duration":0,"x":410.25,"y":89.55}]},{"name":"j_1","translateFrame":[{"duration":15,"tweenEasing":0},{"duration":3,"tweenEasing":0,"x":-3.17,"y":-102.55},{"duration":32,"x":-3.17,"y":-7.87}],"scaleFrame":[{"duration":15,"tweenEasing":0},{"duration":35,"x":-0.93,"y":0.93}]},{"name":"j2","translateFrame":[{"duration":30,"tweenEasing":0},{"duration":3,"tweenEasing":0,"x":57.75,"y":-116.04},{"duration":17,"x":57.75,"y":-9.21}],"scaleFrame":[{"duration":30,"tweenEasing":0},{"duration":20,"x":-0.75,"y":0.75}]},{"name":"j2_2","translateFrame":[{"duration":35,"tweenEasing":0},{"duration":5,"tweenEasing":0,"x":58.07,"y":-9.26},{"duration":10,"x":58.07,"y":48}],"scaleFrame":[{"duration":35,"tweenEasing":0},{"duration":5,"tweenEasing":0,"x":-0.75,"y":0.75},{"duration":10,"x":-2.5,"y":2.5}]},{"name":"j_1_1","translateFrame":[{"duration":20,"tweenEasing":0},{"duration":5,"tweenEasing":0,"x":-3.51,"y":-7.54},{"duration":25,"x":-3.51,"y":54.12}],"scaleFrame":[{"duration":20,"tweenEasing":0},{"duration":5,"tweenEasing":0,"x":-0.93,"y":0.93},{"duration":25,"x":-2.5,"y":2.5}]},{"name":"j_3","translateFrame":[{"duration":3,"tweenEasing":0,"x":-70.53,"y":-104.82},{"duration":47,"x":-70.53,"y":-20.44}],"scaleFrame":[{"duration":50,"x":-0.75,"y":0.75}]},{"name":"j_3_3","translateFrame":[{"duration":5,"tweenEasing":0},{"duration":5,"tweenEasing":0,"x":-70.92,"y":-20.54},{"duration":40,"x":-70.92,"y":24.5}],"scaleFrame":[{"duration":5,"tweenEasing":0},{"duration":5,"tweenEasing":0,"x":-0.75,"y":0.75},{"duration":40,"x":-2.5,"y":2.5}]}],"slot":[{"name":"jl_1","displayFrame":[{"duration":15,"value":-1},{"duration":35}],"colorFrame":[{"duration":15,"tweenEasing":0},{"duration":3,"tweenEasing":0,"value":{"aM":0}},{"duration":32}]},{"name":"jl_2","displayFrame":[{"duration":50}],"colorFrame":[{"duration":3,"tweenEasing":0,"value":{"aM":0}},{"duration":47}]},{"name":"jl_3","displayFrame":[{"duration":30,"value":-1},{"duration":20}],"colorFrame":[{"duration":30,"tweenEasing":0},{"duration":3,"tweenEasing":0,"value":{"aM":0}},{"duration":17}]},{"name":"jl_4","displayFrame":[{"duration":35,"value":-1},{"duration":15}],"colorFrame":[{"duration":37,"tweenEasing":0},{"duration":3,"tweenEasing":0},{"duration":10,"value":{"aM":0}}]},{"name":"jl_5","displayFrame":[{"duration":20,"value":-1},{"duration":30}],"colorFrame":[{"duration":22,"tweenEasing":0},{"duration":3,"tweenEasing":0},{"duration":25,"value":{"aM":0}}]},{"name":"jl_6","displayFrame":[{"duration":5,"value":-1},{"duration":45}],"colorFrame":[{"duration":7,"tweenEasing":0},{"duration":3,"tweenEasing":0},{"duration":40,"value":{"aM":0}}]},{"name":"xxxx_1","displayFrame":[{"duration":5,"value":-1},{"duration":10,"value":2},{"duration":5,"value":-1},{"duration":10,"value":2},{"duration":5,"value":-1},{"duration":10,"value":2},{"duration":5,"value":-1}],"colorFrame":[{"duration":10,"tweenEasing":0},{"duration":5,"tweenEasing":0},{"duration":5,"tweenEasing":0,"value":{"aM":0}},{"duration":5,"tweenEasing":0},{"duration":5,"tweenEasing":0},{"duration":5,"tweenEasing":0,"value":{"aM":0}},{"duration":5,"tweenEasing":0},{"duration":5,"tweenEasing":0},{"duration":5,"value":{"aM":0}}]},{"name":"xxxx_7","displayFrame":[{"duration":5,"value":-1},{"duration":10,"value":2},{"duration":5,"value":-1},{"duration":10,"value":2},{"duration":5,"value":-1},{"duration":10,"value":2},{"duration":5,"value":-1}],"colorFrame":[{"duration":10,"tweenEasing":0},{"duration":5,"tweenEasing":0},{"duration":5,"tweenEasing":0,"value":{"aM":0}},{"duration":5,"tweenEasing":0},{"duration":5,"tweenEasing":0},{"duration":5,"tweenEasing":0,"value":{"aM":0}},{"duration":5,"tweenEasing":0},{"duration":5,"tweenEasing":0},{"duration":5,"value":{"aM":0}}]},{"name":"xxxx_8","displayFrame":[{"duration":5,"value":-1},{"duration":10,"value":2},{"duration":5,"value":-1},{"duration":10,"value":2},{"duration":5,"value":-1},{"duration":10,"value":2},{"duration":5,"value":-1}],"colorFrame":[{"duration":10,"tweenEasing":0},{"duration":5,"tweenEasing":0},{"duration":5,"tweenEasing":0,"value":{"aM":0}},{"duration":5,"tweenEasing":0},{"duration":5,"tweenEasing":0},{"duration":5,"tweenEasing":0,"value":{"aM":0}},{"duration":5,"tweenEasing":0},{"duration":5,"tweenEasing":0},{"duration":5,"value":{"aM":0}}]},{"name":"xxxx_9","displayFrame":[{"duration":5,"value":-1},{"duration":10,"value":2},{"duration":5,"value":-1},{"duration":10,"value":2},{"duration":5,"value":-1},{"duration":10,"value":2},{"duration":5,"value":-1}],"colorFrame":[{"duration":10,"tweenEasing":0},{"duration":5,"tweenEasing":0},{"duration":5,"tweenEasing":0,"value":{"aM":0}},{"duration":5,"tweenEasing":0},{"duration":5,"tweenEasing":0},{"duration":5,"tweenEasing":0,"value":{"aM":0}},{"duration":5,"tweenEasing":0},{"duration":5,"tweenEasing":0},{"duration":5,"value":{"aM":0}}]},{"name":"xxxx_10","displayFrame":[{"duration":10,"value":-1},{"duration":10,"value":2},{"duration":5,"value":-1},{"duration":10,"value":2},{"duration":5,"value":-1},{"duration":10,"value":2},{"duration":0,"value":-1}],"colorFrame":[{"duration":15,"tweenEasing":0},{"duration":5,"tweenEasing":0},{"duration":5,"tweenEasing":0,"value":{"aM":0}},{"duration":5,"tweenEasing":0},{"duration":5,"tweenEasing":0},{"duration":5,"tweenEasing":0,"value":{"aM":0}},{"duration":5,"tweenEasing":0},{"duration":5,"tweenEasing":0},{"duration":0,"value":{"aM":0}}]},{"name":"xxxx_11","displayFrame":[{"duration":10,"value":-1},{"duration":10,"value":2},{"duration":5,"value":-1},{"duration":10,"value":2},{"duration":5,"value":-1},{"duration":10,"value":2},{"duration":0,"value":-1}],"colorFrame":[{"duration":15,"tweenEasing":0},{"duration":5,"tweenEasing":0},{"duration":5,"tweenEasing":0,"value":{"aM":0}},{"duration":5,"tweenEasing":0},{"duration":5,"tweenEasing":0},{"duration":5,"tweenEasing":0,"value":{"aM":0}},{"duration":5,"tweenEasing":0},{"duration":5,"tweenEasing":0},{"duration":0,"value":{"aM":0}}]},{"name":"xxxx_12","displayFrame":[{"duration":10,"value":-1},{"duration":10,"value":2},{"duration":5,"value":-1},{"duration":10,"value":2},{"duration":5,"value":-1},{"duration":10,"value":2},{"duration":0,"value":-1}],"colorFrame":[{"duration":15,"tweenEasing":0},{"duration":5,"tweenEasing":0},{"duration":5,"tweenEasing":0,"value":{"aM":0}},{"duration":5,"tweenEasing":0},{"duration":5,"tweenEasing":0},{"duration":5,"tweenEasing":0,"value":{"aM":0}},{"duration":5,"tweenEasing":0},{"duration":5,"tweenEasing":0},{"duration":0,"value":{"aM":0}}]},{"name":"xxxx_13","displayFrame":[{"duration":10,"value":-1},{"duration":10,"value":2},{"duration":5,"value":-1},{"duration":10,"value":2},{"duration":5,"value":-1},{"duration":10,"value":2},{"duration":0,"value":-1}],"colorFrame":[{"duration":15,"tweenEasing":0},{"duration":5,"tweenEasing":0},{"duration":5,"tweenEasing":0,"value":{"aM":0}},{"duration":5,"tweenEasing":0},{"duration":5,"tweenEasing":0},{"duration":5,"tweenEasing":0,"value":{"aM":0}},{"duration":5,"tweenEasing":0},{"duration":5,"tweenEasing":0},{"duration":0,"value":{"aM":0}}]}]},{"duration":20,"name":"attack_t_1","bone":[{"name":"bone4","translateFrame":[{"duration":5,"tweenEasing":0},{"duration":10,"tweenEasing":0,"x":241.55,"y":184.92},{"duration":5,"x":117.28,"y":186.59}]},{"name":"bone5","translateFrame":[{"duration":5,"tweenEasing":0},{"duration":10,"tweenEasing":0,"x":293.51,"y":152.14},{"duration":5,"x":421.37,"y":156.16}]},{"name":"bone6","translateFrame":[{"duration":5,"tweenEasing":0},{"duration":10,"tweenEasing":0,"x":323.71,"y":99.27},{"duration":5,"x":411.86,"y":7.17}]},{"name":"bone7","translateFrame":[{"duration":5,"tweenEasing":0},{"duration":10,"tweenEasing":0,"x":327.49,"y":32.25},{"duration":5,"x":256.38,"y":-67.95}]},{"name":"t_1","translateFrame":[{"duration":3,"tweenEasing":0,"x":6.5,"y":-87.61},{"duration":17,"x":6.5,"y":9.67}]},{"name":"t_2","translateFrame":[{"duration":5,"tweenEasing":0},{"duration":5,"tweenEasing":0,"x":6.85,"y":9.5},{"duration":10,"x":6.85,"y":44.21}],"scaleFrame":[{"duration":5,"tweenEasing":0},{"duration":5,"tweenEasing":0},{"duration":10,"x":2.5,"y":2.5}]},{"name":"bone8","translateFrame":[{"duration":10,"tweenEasing":0},{"duration":10,"tweenEasing":0,"x":167.63,"y":170.94},{"duration":0,"x":242.83,"y":63.27}]},{"name":"bone9","translateFrame":[{"duration":10,"tweenEasing":0},{"duration":10,"tweenEasing":0,"x":152.36,"y":132.78},{"duration":0,"x":152.24,"y":8.96}]},{"name":"bone10","translateFrame":[{"duration":10,"tweenEasing":0},{"duration":10,"tweenEasing":0,"x":207.48,"y":146.35},{"duration":0,"x":87.76,"y":84.44}]},{"name":"bone11","translateFrame":[{"duration":10,"tweenEasing":0},{"duration":10,"tweenEasing":0,"x":254.12,"y":123.45},{"duration":0,"x":389.73,"y":91.02}]}],"slot":[{"name":"tl_1","displayFrame":[{"duration":20}],"colorFrame":[{"duration":3,"tweenEasing":0,"value":{"aM":0}},{"duration":17}]},{"name":"tl_2","displayFrame":[{"duration":5,"value":-1},{"duration":15}],"colorFrame":[{"duration":7,"tweenEasing":0},{"duration":3,"tweenEasing":0},{"duration":10,"value":{"aM":0}}]},{"name":"xxxx_1","displayFrame":[{"duration":5,"value":-1},{"duration":10},{"duration":5,"value":-1}],"colorFrame":[{"duration":12,"tweenEasing":0},{"duration":3,"tweenEasing":0},{"duration":5,"value":{"aM":0}}]},{"name":"xxxx_7","displayFrame":[{"duration":5,"value":-1},{"duration":10},{"duration":5,"value":-1}],"colorFrame":[{"duration":12,"tweenEasing":0},{"duration":3,"tweenEasing":0},{"duration":5,"value":{"aM":0}}]},{"name":"xxxx_8","displayFrame":[{"duration":5,"value":-1},{"duration":10},{"duration":5,"value":-1}],"colorFrame":[{"duration":12,"tweenEasing":0},{"duration":3,"tweenEasing":0},{"duration":5,"value":{"aM":0}}]},{"name":"xxxx_9","displayFrame":[{"duration":5,"value":-1},{"duration":10},{"duration":5,"value":-1}],"colorFrame":[{"duration":12,"tweenEasing":0},{"duration":3,"tweenEasing":0},{"duration":5,"value":{"aM":0}}]},{"name":"xxxx_10","displayFrame":[{"duration":10,"value":-1},{"duration":10},{"duration":0,"value":-1}],"colorFrame":[{"duration":15,"tweenEasing":0},{"duration":5,"tweenEasing":0},{"duration":0,"value":{"aM":0}}]},{"name":"xxxx_11","displayFrame":[{"duration":10,"value":-1},{"duration":10},{"duration":0,"value":-1}],"colorFrame":[{"duration":15,"tweenEasing":0},{"duration":5,"tweenEasing":0},{"duration":0,"value":{"aM":0}}]},{"name":"xxxx_12","displayFrame":[{"duration":10,"value":-1},{"duration":10},{"duration":0,"value":-1}],"colorFrame":[{"duration":15,"tweenEasing":0},{"duration":5,"tweenEasing":0},{"duration":0,"value":{"aM":0}}]},{"name":"xxxx_13","displayFrame":[{"duration":10,"value":-1},{"duration":10},{"duration":0,"value":-1}],"colorFrame":[{"duration":15,"tweenEasing":0},{"duration":5,"tweenEasing":0},{"duration":0,"value":{"aM":0}}]}]},{"duration":20,"name":"attack_t_2","bone":[{"name":"bone4","translateFrame":[{"duration":5,"tweenEasing":0},{"duration":10,"tweenEasing":0,"x":230.87,"y":184.92},{"duration":5,"x":110.97,"y":186.59}]},{"name":"bone5","translateFrame":[{"duration":5,"tweenEasing":0},{"duration":10,"tweenEasing":0,"x":282.82,"y":152.14},{"duration":5,"x":415.05,"y":156.16}]},{"name":"bone6","translateFrame":[{"duration":5,"tweenEasing":0},{"duration":10,"tweenEasing":0,"x":313.03,"y":99.27},{"duration":5,"x":405.55,"y":7.17}]},{"name":"bone7","translateFrame":[{"duration":5,"tweenEasing":0},{"duration":10,"tweenEasing":0,"x":316.81,"y":32.25},{"duration":5,"x":250.07,"y":-67.95}]},{"name":"t_1","translateFrame":[{"duration":3,"tweenEasing":0,"x":-2.88,"y":-87.61},{"duration":17,"x":-2.88,"y":10.35}]},{"name":"t_2","translateFrame":[{"duration":5,"tweenEasing":0},{"duration":5,"tweenEasing":0,"x":-2.88,"y":9.5},{"duration":10,"x":-2.88,"y":44.21}],"scaleFrame":[{"duration":5,"tweenEasing":0},{"duration":5,"tweenEasing":0},{"duration":10,"x":2.5,"y":2.5}]},{"name":"bone8","translateFrame":[{"duration":10,"tweenEasing":0},{"duration":10,"tweenEasing":0,"x":158.35,"y":170.94},{"duration":0,"x":231.24,"y":63.27}]},{"name":"bone9","translateFrame":[{"duration":10,"tweenEasing":0},{"duration":10,"tweenEasing":0,"x":143.09,"y":132.78},{"duration":0,"x":140.65,"y":8.96}]},{"name":"bone10","translateFrame":[{"duration":10,"tweenEasing":0},{"duration":10,"tweenEasing":0,"x":198.21,"y":146.35},{"duration":0,"x":76.17,"y":84.44}]},{"name":"bone11","translateFrame":[{"duration":10,"tweenEasing":0},{"duration":10,"tweenEasing":0,"x":244.85,"y":123.45},{"duration":0,"x":378.14,"y":91.02}]}],"slot":[{"name":"tl_1","displayFrame":[{"duration":20}],"colorFrame":[{"duration":3,"tweenEasing":0,"value":{"aM":0}},{"duration":17}]},{"name":"tl_2","displayFrame":[{"duration":5,"value":-1},{"duration":15}],"colorFrame":[{"duration":7,"tweenEasing":0},{"duration":3,"tweenEasing":0},{"duration":10,"value":{"aM":0}}]},{"name":"xxxx_1","displayFrame":[{"duration":5,"value":-1},{"duration":10},{"duration":5,"value":-1}],"colorFrame":[{"duration":12,"tweenEasing":0},{"duration":3,"tweenEasing":0},{"duration":5,"value":{"aM":0}}]},{"name":"xxxx_7","displayFrame":[{"duration":5,"value":-1},{"duration":10},{"duration":5,"value":-1}],"colorFrame":[{"duration":12,"tweenEasing":0},{"duration":3,"tweenEasing":0},{"duration":5,"value":{"aM":0}}]},{"name":"xxxx_8","displayFrame":[{"duration":5,"value":-1},{"duration":10},{"duration":5,"value":-1}],"colorFrame":[{"duration":12,"tweenEasing":0},{"duration":3,"tweenEasing":0},{"duration":5,"value":{"aM":0}}]},{"name":"xxxx_9","displayFrame":[{"duration":5,"value":-1},{"duration":10},{"duration":5,"value":-1}],"colorFrame":[{"duration":12,"tweenEasing":0},{"duration":3,"tweenEasing":0},{"duration":5,"value":{"aM":0}}]},{"name":"xxxx_10","displayFrame":[{"duration":10,"value":-1},{"duration":10},{"duration":0,"value":-1}],"colorFrame":[{"duration":15,"tweenEasing":0},{"duration":5,"tweenEasing":0},{"duration":0,"value":{"aM":0}}]},{"name":"xxxx_11","displayFrame":[{"duration":10,"value":-1},{"duration":10},{"duration":0,"value":-1}],"colorFrame":[{"duration":15,"tweenEasing":0},{"duration":5,"tweenEasing":0},{"duration":0,"value":{"aM":0}}]},{"name":"xxxx_12","displayFrame":[{"duration":10,"value":-1},{"duration":10},{"duration":0,"value":-1}],"colorFrame":[{"duration":15,"tweenEasing":0},{"duration":5,"tweenEasing":0},{"duration":0,"value":{"aM":0}}]},{"name":"xxxx_13","displayFrame":[{"duration":10,"value":-1},{"duration":10},{"duration":0,"value":-1}],"colorFrame":[{"duration":15,"tweenEasing":0},{"duration":5,"tweenEasing":0},{"duration":0,"value":{"aM":0}}]}]},{"duration":20,"name":"attack_t_3","bone":[{"name":"bone4","translateFrame":[{"duration":5,"tweenEasing":0},{"duration":10,"tweenEasing":0,"x":227.91,"y":184.92},{"duration":5,"x":102.51,"y":186.59}]},{"name":"bone5","translateFrame":[{"duration":5,"tweenEasing":0},{"duration":10,"tweenEasing":0,"x":279.86,"y":152.14},{"duration":5,"x":406.6,"y":156.16}]},{"name":"bone6","translateFrame":[{"duration":5,"tweenEasing":0},{"duration":10,"tweenEasing":0,"x":310.07,"y":99.27},{"duration":5,"x":397.09,"y":7.17}]},{"name":"bone7","translateFrame":[{"duration":5,"tweenEasing":0},{"duration":10,"tweenEasing":0,"x":313.85,"y":32.25},{"duration":5,"x":241.61,"y":-67.95}]},{"name":"t_1","translateFrame":[{"duration":3,"tweenEasing":0,"x":-4.75,"y":-87.61},{"duration":17,"x":-4.75,"y":9.67}],"scaleFrame":[{"duration":20,"x":-1}]},{"name":"t_2","translateFrame":[{"duration":5,"tweenEasing":0},{"duration":5,"tweenEasing":0,"x":-4.97,"y":9.63},{"duration":10,"x":-4.97,"y":44.21}],"scaleFrame":[{"duration":5,"tweenEasing":0},{"duration":5,"tweenEasing":0,"x":-1},{"duration":10,"x":-2.5,"y":2.5}]},{"name":"bone8","translateFrame":[{"duration":10,"tweenEasing":0},{"duration":10,"tweenEasing":0,"x":152.24,"y":169.02},{"duration":0,"x":218.38,"y":63.27}]},{"name":"bone9","translateFrame":[{"duration":10,"tweenEasing":0},{"duration":10,"tweenEasing":0,"x":136.97,"y":130.86},{"duration":0,"x":127.79,"y":8.96}]},{"name":"bone10","translateFrame":[{"duration":10,"tweenEasing":0},{"duration":10,"tweenEasing":0,"x":192.09,"y":144.42},{"duration":0,"x":63.31,"y":84.44}]},{"name":"bone11","translateFrame":[{"duration":10,"tweenEasing":0},{"duration":10,"tweenEasing":0,"x":238.73,"y":121.53},{"duration":0,"x":365.28,"y":91.02}]}],"slot":[{"name":"tl_1","displayFrame":[{"duration":20}],"colorFrame":[{"duration":3,"tweenEasing":0,"value":{"aM":0}},{"duration":17}]},{"name":"tl_2","displayFrame":[{"duration":5,"value":-1},{"duration":15}],"colorFrame":[{"duration":7,"tweenEasing":0},{"duration":3,"tweenEasing":0},{"duration":10,"value":{"aM":0}}]},{"name":"xxxx_1","displayFrame":[{"duration":5,"value":-1},{"duration":10},{"duration":5,"value":-1}],"colorFrame":[{"duration":12,"tweenEasing":0},{"duration":3,"tweenEasing":0},{"duration":5,"value":{"aM":0}}]},{"name":"xxxx_7","displayFrame":[{"duration":5,"value":-1},{"duration":10},{"duration":5,"value":-1}],"colorFrame":[{"duration":12,"tweenEasing":0},{"duration":3,"tweenEasing":0},{"duration":5,"value":{"aM":0}}]},{"name":"xxxx_8","displayFrame":[{"duration":5,"value":-1},{"duration":10},{"duration":5,"value":-1}],"colorFrame":[{"duration":12,"tweenEasing":0},{"duration":3,"tweenEasing":0},{"duration":5,"value":{"aM":0}}]},{"name":"xxxx_9","displayFrame":[{"duration":5,"value":-1},{"duration":10},{"duration":5,"value":-1}],"colorFrame":[{"duration":12,"tweenEasing":0},{"duration":3,"tweenEasing":0},{"duration":5,"value":{"aM":0}}]},{"name":"xxxx_10","displayFrame":[{"duration":10,"value":-1},{"duration":10},{"duration":0,"value":-1}],"colorFrame":[{"duration":15,"tweenEasing":0},{"duration":5,"tweenEasing":0},{"duration":0,"value":{"aM":0}}]},{"name":"xxxx_11","displayFrame":[{"duration":10,"value":-1},{"duration":10},{"duration":0,"value":-1}],"colorFrame":[{"duration":15,"tweenEasing":0},{"duration":5,"tweenEasing":0},{"duration":0,"value":{"aM":0}}]},{"name":"xxxx_12","displayFrame":[{"duration":10,"value":-1},{"duration":10},{"duration":0,"value":-1}],"colorFrame":[{"duration":15,"tweenEasing":0},{"duration":5,"tweenEasing":0},{"duration":0,"value":{"aM":0}}]},{"name":"xxxx_13","displayFrame":[{"duration":10,"value":-1},{"duration":10},{"duration":0,"value":-1}],"colorFrame":[{"duration":15,"tweenEasing":0},{"duration":5,"tweenEasing":0},{"duration":0,"value":{"aM":0}}]}]},{"duration":35,"name":"attack_y_1","bone":[{"name":"bone4","translateFrame":[{"duration":5,"tweenEasing":0},{"duration":10,"tweenEasing":0,"x":226.28,"y":190.14},{"duration":5,"tweenEasing":0,"x":104.2,"y":186.59},{"duration":10,"tweenEasing":0,"x":254.17,"y":181.61},{"duration":5,"x":136.48,"y":152.13}]},{"name":"bone5","translateFrame":[{"duration":5,"tweenEasing":0},{"duration":10,"tweenEasing":0,"x":278.24,"y":157.35},{"duration":5,"tweenEasing":0,"x":408.28,"y":156.16},{"duration":10,"tweenEasing":0,"x":306.13,"y":148.83},{"duration":5,"x":440.56,"y":121.69}]},{"name":"bone6","translateFrame":[{"duration":5,"tweenEasing":0},{"duration":10,"tweenEasing":0,"x":308.45,"y":104.49},{"duration":5,"tweenEasing":0,"x":398.77,"y":7.17},{"duration":10,"tweenEasing":0,"x":336.34,"y":95.96},{"duration":5,"x":431.05,"y":-27.28}]},{"name":"bone7","translateFrame":[{"duration":5,"tweenEasing":0},{"duration":10,"tweenEasing":0,"x":312.22,"y":37.47},{"duration":5,"tweenEasing":0,"x":243.3,"y":-67.95},{"duration":10,"tweenEasing":0,"x":340.11,"y":28.94},{"duration":5,"x":275.57,"y":-102.41}]},{"name":"bone8","translateFrame":[{"duration":10,"tweenEasing":0},{"duration":10,"tweenEasing":0,"x":151.64,"y":173.44},{"duration":5,"tweenEasing":0,"x":223.74,"y":63.27},{"duration":10,"tweenEasing":0,"x":179.19,"y":164.56},{"duration":0,"x":245.59,"y":63.27}]},{"name":"bone9","translateFrame":[{"duration":10,"tweenEasing":0},{"duration":10,"tweenEasing":0,"x":136.38,"y":135.28},{"duration":5,"tweenEasing":0,"x":133.14,"y":8.96},{"duration":10,"tweenEasing":0,"x":163.92,"y":126.4},{"duration":0,"x":154.99,"y":8.96}]},{"name":"bone10","translateFrame":[{"duration":10,"tweenEasing":0},{"duration":10,"tweenEasing":0,"x":191.5,"y":148.85},{"duration":5,"tweenEasing":0,"x":68.66,"y":84.44},{"duration":10,"tweenEasing":0,"x":219.04,"y":139.97},{"duration":0,"x":90.52,"y":84.44}]},{"name":"bone11","translateFrame":[{"duration":10,"tweenEasing":0},{"duration":10,"tweenEasing":0,"x":238.14,"y":125.95},{"duration":5,"tweenEasing":0,"x":370.63,"y":91.02},{"duration":10,"tweenEasing":0,"x":265.68,"y":117.07},{"duration":0,"x":392.49,"y":91.02}]},{"name":"y_1","translateFrame":[{"duration":3,"tweenEasing":0,"x":-8.58,"y":-87.86},{"duration":32,"x":-8.58,"y":10.34}],"scaleFrame":[{"duration":35,"x":0.9,"y":0.9}]},{"name":"y_1_1","translateFrame":[{"duration":5,"tweenEasing":0},{"duration":5,"tweenEasing":0,"x":-8.74,"y":10.33},{"duration":25,"x":-8.74,"y":52.36}],"scaleFrame":[{"duration":5,"tweenEasing":0},{"duration":5,"tweenEasing":0,"x":0.9,"y":0.9},{"duration":25,"x":2.5,"y":2.5}]},{"name":"y_2","translateFrame":[{"duration":15,"tweenEasing":0},{"duration":3,"tweenEasing":0,"x":18.32,"y":-87.03},{"duration":17,"x":18.32,"y":0.35}],"scaleFrame":[{"duration":15,"tweenEasing":0},{"duration":20,"x":0.9,"y":0.9}]},{"name":"y_2_2","translateFrame":[{"duration":20,"tweenEasing":0},{"duration":5,"tweenEasing":0,"x":18.46},{"duration":10,"x":18.46,"y":41.7}],"scaleFrame":[{"duration":20,"tweenEasing":0},{"duration":5,"tweenEasing":0,"x":0.9,"y":0.9},{"duration":10,"x":2.5,"y":2.5}]}],"slot":[{"name":"xxxx_1","displayFrame":[{"duration":5,"value":-1},{"duration":10,"value":1},{"duration":5,"value":-1},{"duration":10,"value":1},{"duration":5,"value":-1}],"colorFrame":[{"duration":10,"tweenEasing":0},{"duration":5,"tweenEasing":0},{"duration":5,"tweenEasing":0,"value":{"aM":0}},{"duration":5,"tweenEasing":0},{"duration":5,"tweenEasing":0},{"duration":5,"value":{"aM":0}}]},{"name":"xxxx_7","displayFrame":[{"duration":5,"value":-1},{"duration":10,"value":1},{"duration":5,"value":-1},{"duration":10,"value":1},{"duration":5,"value":-1}],"colorFrame":[{"duration":10,"tweenEasing":0},{"duration":5,"tweenEasing":0},{"duration":5,"tweenEasing":0,"value":{"aM":0}},{"duration":5,"tweenEasing":0},{"duration":5,"tweenEasing":0},{"duration":5,"value":{"aM":0}}]},{"name":"xxxx_8","displayFrame":[{"duration":5,"value":-1},{"duration":10,"value":1},{"duration":5,"value":-1},{"duration":10,"value":1},{"duration":5,"value":-1}],"colorFrame":[{"duration":10,"tweenEasing":0},{"duration":5,"tweenEasing":0},{"duration":5,"tweenEasing":0,"value":{"aM":0}},{"duration":5,"tweenEasing":0},{"duration":5,"tweenEasing":0},{"duration":5,"value":{"aM":0}}]},{"name":"xxxx_9","displayFrame":[{"duration":5,"value":-1},{"duration":10,"value":1},{"duration":5,"value":-1},{"duration":10,"value":1},{"duration":5,"value":-1}],"colorFrame":[{"duration":10,"tweenEasing":0},{"duration":5,"tweenEasing":0},{"duration":5,"tweenEasing":0,"value":{"aM":0}},{"duration":5,"tweenEasing":0},{"duration":5,"tweenEasing":0},{"duration":5,"value":{"aM":0}}]},{"name":"xxxx_10","displayFrame":[{"duration":10,"value":-1},{"duration":10,"value":1},{"duration":5,"value":-1},{"duration":10,"value":1},{"duration":0,"value":-1}],"colorFrame":[{"duration":15,"tweenEasing":0},{"duration":5,"tweenEasing":0},{"duration":5,"tweenEasing":0,"value":{"aM":0}},{"duration":5,"tweenEasing":0},{"duration":5,"tweenEasing":0},{"duration":0,"value":{"aM":0}}]},{"name":"xxxx_11","displayFrame":[{"duration":10,"value":-1},{"duration":10,"value":1},{"duration":5,"value":-1},{"duration":10,"value":1},{"duration":0,"value":-1}],"colorFrame":[{"duration":15,"tweenEasing":0},{"duration":5,"tweenEasing":0},{"duration":5,"tweenEasing":0,"value":{"aM":0}},{"duration":5,"tweenEasing":0},{"duration":5,"tweenEasing":0},{"duration":0,"value":{"aM":0}}]},{"name":"xxxx_12","displayFrame":[{"duration":10,"value":-1},{"duration":10,"value":1},{"duration":5,"value":-1},{"duration":10,"value":1},{"duration":0,"value":-1}],"colorFrame":[{"duration":15,"tweenEasing":0},{"duration":5,"tweenEasing":0},{"duration":5,"tweenEasing":0,"value":{"aM":0}},{"duration":5,"tweenEasing":0},{"duration":5,"tweenEasing":0},{"duration":0,"value":{"aM":0}}]},{"name":"xxxx_13","displayFrame":[{"duration":10,"value":-1},{"duration":10,"value":1},{"duration":5,"value":-1},{"duration":10,"value":1},{"duration":0,"value":-1}],"colorFrame":[{"duration":15,"tweenEasing":0},{"duration":5,"tweenEasing":0},{"duration":5,"tweenEasing":0,"value":{"aM":0}},{"duration":5,"tweenEasing":0},{"duration":5,"tweenEasing":0},{"duration":0,"value":{"aM":0}}]},{"name":"yl_1","displayFrame":[{"duration":35}],"colorFrame":[{"duration":3,"tweenEasing":0,"value":{"aM":0}},{"duration":32}]},{"name":"yl_2","displayFrame":[{"duration":5,"value":-1},{"duration":30}],"colorFrame":[{"duration":7,"tweenEasing":0},{"duration":3,"tweenEasing":0},{"duration":25,"value":{"aM":0}}]},{"name":"yl_3","displayFrame":[{"duration":15,"value":-1},{"duration":20}],"colorFrame":[{"duration":15,"tweenEasing":0},{"duration":3,"tweenEasing":0,"value":{"aM":0}},{"duration":17}]},{"name":"yl_4","displayFrame":[{"duration":20,"value":-1},{"duration":15}],"colorFrame":[{"duration":22,"tweenEasing":0},{"duration":3,"tweenEasing":0},{"duration":10,"value":{"aM":0}}]}]},{"duration":35,"name":"attack_y_2","bone":[{"name":"bone4","translateFrame":[{"duration":5,"tweenEasing":0},{"duration":10,"tweenEasing":0,"x":205.04,"y":183.22},{"duration":5,"tweenEasing":0,"x":85.92,"y":186.59},{"duration":10,"tweenEasing":0,"x":260.1,"y":181.61},{"duration":5,"x":143.89,"y":152.13}]},{"name":"bone5","translateFrame":[{"duration":5,"tweenEasing":0},{"duration":10,"tweenEasing":0,"x":257,"y":150.44},{"duration":5,"tweenEasing":0,"x":390,"y":156.16},{"duration":10,"tweenEasing":0,"x":312.06,"y":148.83},{"duration":5,"x":447.98,"y":121.69}]},{"name":"bone6","translateFrame":[{"duration":5,"tweenEasing":0},{"duration":10,"tweenEasing":0,"x":287.2,"y":97.57},{"duration":5,"tweenEasing":0,"x":380.5,"y":7.17},{"duration":10,"tweenEasing":0,"x":342.27,"y":95.96},{"duration":5,"x":438.47,"y":-27.28}]},{"name":"bone7","translateFrame":[{"duration":5,"tweenEasing":0},{"duration":10,"tweenEasing":0,"x":290.98,"y":30.55},{"duration":5,"tweenEasing":0,"x":225.02,"y":-67.95},{"duration":10,"tweenEasing":0,"x":346.04,"y":28.94},{"duration":5,"x":282.99,"y":-102.41}]},{"name":"bone8","translateFrame":[{"duration":10,"tweenEasing":0},{"duration":10,"tweenEasing":0,"x":130.9,"y":167.34},{"duration":5,"tweenEasing":0,"x":212.76,"y":63.27},{"duration":10,"tweenEasing":0,"x":185.29,"y":162.73},{"duration":0,"x":254.13,"y":63.27}]},{"name":"bone9","translateFrame":[{"duration":10,"tweenEasing":0},{"duration":10,"tweenEasing":0,"x":115.64,"y":129.18},{"duration":5,"tweenEasing":0,"x":122.16,"y":8.96},{"duration":10,"tweenEasing":0,"x":170.02,"y":124.57},{"duration":0,"x":163.53,"y":8.96}]},{"name":"bone10","translateFrame":[{"duration":10,"tweenEasing":0},{"duration":10,"tweenEasing":0,"x":170.76,"y":142.75},{"duration":5,"tweenEasing":0,"x":57.68,"y":84.44},{"duration":10,"tweenEasing":0,"x":225.14,"y":138.14},{"duration":0,"x":99.06,"y":84.44}]},{"name":"bone11","translateFrame":[{"duration":10,"tweenEasing":0},{"duration":10,"tweenEasing":0,"x":217.4,"y":119.85},{"duration":5,"tweenEasing":0,"x":359.65,"y":91.02},{"duration":10,"tweenEasing":0,"x":271.78,"y":115.24},{"duration":0,"x":401.03,"y":91.02}]},{"name":"y_1","translateFrame":[{"duration":3,"tweenEasing":0,"x":-30.03,"y":-87.86},{"duration":32,"x":-30.04,"y":6.19}],"scaleFrame":[{"duration":3,"tweenEasing":0,"x":0.9,"y":0.9},{"duration":32}]},{"name":"y_1_1","translateFrame":[{"duration":5,"tweenEasing":0},{"duration":5,"tweenEasing":0,"x":-30.03,"y":5.75},{"duration":25,"x":-30.03,"y":52.36}],"scaleFrame":[{"duration":5,"tweenEasing":0},{"duration":5,"tweenEasing":0},{"duration":25,"x":2.5,"y":2.5}]},{"name":"y_2","translateFrame":[{"duration":15,"tweenEasing":0},{"duration":3,"tweenEasing":0,"x":23.93,"y":-87.03},{"duration":17,"x":23.92,"y":6.25}]},{"name":"y_2_2","translateFrame":[{"duration":20,"tweenEasing":0},{"duration":5,"tweenEasing":0,"x":23.93,"y":6.29},{"duration":10,"x":23.93,"y":41.7}],"scaleFrame":[{"duration":20,"tweenEasing":0},{"duration":5,"tweenEasing":0},{"duration":10,"x":2.5,"y":2.5}]}],"slot":[{"name":"xxxx_1","displayFrame":[{"duration":5,"value":-1},{"duration":10,"value":1},{"duration":5,"value":-1},{"duration":10,"value":1},{"duration":5,"value":-1}],"colorFrame":[{"duration":10,"tweenEasing":0},{"duration":5,"tweenEasing":0},{"duration":5,"tweenEasing":0,"value":{"aM":0}},{"duration":5,"tweenEasing":0},{"duration":5,"tweenEasing":0},{"duration":5,"value":{"aM":0}}]},{"name":"xxxx_7","displayFrame":[{"duration":5,"value":-1},{"duration":10,"value":1},{"duration":5,"value":-1},{"duration":10,"value":1},{"duration":5,"value":-1}],"colorFrame":[{"duration":10,"tweenEasing":0},{"duration":5,"tweenEasing":0},{"duration":5,"tweenEasing":0,"value":{"aM":0}},{"duration":5,"tweenEasing":0},{"duration":5,"tweenEasing":0},{"duration":5,"value":{"aM":0}}]},{"name":"xxxx_8","displayFrame":[{"duration":5,"value":-1},{"duration":10,"value":1},{"duration":5,"value":-1},{"duration":10,"value":1},{"duration":5,"value":-1}],"colorFrame":[{"duration":10,"tweenEasing":0},{"duration":5,"tweenEasing":0},{"duration":5,"tweenEasing":0,"value":{"aM":0}},{"duration":5,"tweenEasing":0},{"duration":5,"tweenEasing":0},{"duration":5,"value":{"aM":0}}]},{"name":"xxxx_9","displayFrame":[{"duration":5,"value":-1},{"duration":10,"value":1},{"duration":5,"value":-1},{"duration":10,"value":1},{"duration":5,"value":-1}],"colorFrame":[{"duration":10,"tweenEasing":0},{"duration":5,"tweenEasing":0},{"duration":5,"tweenEasing":0,"value":{"aM":0}},{"duration":5,"tweenEasing":0},{"duration":5,"tweenEasing":0},{"duration":5,"value":{"aM":0}}]},{"name":"xxxx_10","displayFrame":[{"duration":10,"value":-1},{"duration":10,"value":1},{"duration":5,"value":-1},{"duration":10,"value":1},{"duration":0,"value":-1}],"colorFrame":[{"duration":15,"tweenEasing":0},{"duration":5,"tweenEasing":0},{"duration":5,"tweenEasing":0,"value":{"aM":0}},{"duration":5,"tweenEasing":0},{"duration":5,"tweenEasing":0},{"duration":0,"value":{"aM":0}}]},{"name":"xxxx_11","displayFrame":[{"duration":10,"value":-1},{"duration":10,"value":1},{"duration":5,"value":-1},{"duration":10,"value":1},{"duration":0,"value":-1}],"colorFrame":[{"duration":15,"tweenEasing":0},{"duration":5,"tweenEasing":0},{"duration":5,"tweenEasing":0,"value":{"aM":0}},{"duration":5,"tweenEasing":0},{"duration":5,"tweenEasing":0},{"duration":0,"value":{"aM":0}}]},{"name":"xxxx_12","displayFrame":[{"duration":10,"value":-1},{"duration":10,"value":1},{"duration":5,"value":-1},{"duration":10,"value":1},{"duration":0,"value":-1}],"colorFrame":[{"duration":15,"tweenEasing":0},{"duration":5,"tweenEasing":0},{"duration":5,"tweenEasing":0,"value":{"aM":0}},{"duration":5,"tweenEasing":0},{"duration":5,"tweenEasing":0},{"duration":0,"value":{"aM":0}}]},{"name":"xxxx_13","displayFrame":[{"duration":10,"value":-1},{"duration":10,"value":1},{"duration":5,"value":-1},{"duration":10,"value":1},{"duration":0,"value":-1}],"colorFrame":[{"duration":15,"tweenEasing":0},{"duration":5,"tweenEasing":0},{"duration":5,"tweenEasing":0,"value":{"aM":0}},{"duration":5,"tweenEasing":0},{"duration":5,"tweenEasing":0},{"duration":0,"value":{"aM":0}}]},{"name":"yl_1","displayFrame":[{"duration":35}],"colorFrame":[{"duration":3,"tweenEasing":0,"value":{"aM":0}},{"duration":32}]},{"name":"yl_2","displayFrame":[{"duration":5,"value":-1},{"duration":30}],"colorFrame":[{"duration":7,"tweenEasing":0},{"duration":3,"tweenEasing":0},{"duration":25,"value":{"aM":0}}]},{"name":"yl_3","displayFrame":[{"duration":15,"value":-1},{"duration":20}],"colorFrame":[{"duration":15,"tweenEasing":0},{"duration":3,"tweenEasing":0,"value":{"aM":0}},{"duration":17}]},{"name":"yl_4","displayFrame":[{"duration":20,"value":-1},{"duration":15}],"colorFrame":[{"duration":22,"tweenEasing":0},{"duration":3,"tweenEasing":0},{"duration":10,"value":{"aM":0}}]}]},{"duration":35,"name":"attack_y_3","bone":[{"name":"bone4","translateFrame":[{"duration":5,"tweenEasing":0},{"duration":10,"tweenEasing":0,"x":214.54,"y":177.78},{"duration":5,"tweenEasing":0,"x":95.54,"y":186.59},{"duration":10,"tweenEasing":0,"x":240.58,"y":182.85},{"duration":5,"x":121.48,"y":197.92}]},{"name":"bone5","translateFrame":[{"duration":5,"tweenEasing":0},{"duration":10,"tweenEasing":0,"x":266.5,"y":144.99},{"duration":5,"tweenEasing":0,"x":399.63,"y":156.16},{"duration":10,"tweenEasing":0,"x":292.53,"y":150.06},{"duration":5,"x":425.57,"y":167.49}]},{"name":"bone6","translateFrame":[{"duration":5,"tweenEasing":0},{"duration":10,"tweenEasing":0,"x":296.7,"y":92.13},{"duration":5,"tweenEasing":0,"x":390.12,"y":7.17},{"duration":10,"tweenEasing":0,"x":322.74,"y":97.2},{"duration":5,"x":416.06,"y":18.5}]},{"name":"bone7","translateFrame":[{"duration":5,"tweenEasing":0},{"duration":10,"tweenEasing":0,"x":300.48,"y":25.11},{"duration":5,"tweenEasing":0,"x":234.64,"y":-67.95},{"duration":10,"tweenEasing":0,"x":326.52,"y":30.17},{"duration":5,"x":260.58,"y":-56.62}]},{"name":"bone8","translateFrame":[{"duration":10,"tweenEasing":0},{"duration":10,"tweenEasing":0,"x":140.78,"y":170.55},{"duration":5,"tweenEasing":0,"x":207.08,"y":63.27},{"duration":10,"tweenEasing":0,"x":167.6,"y":164.56},{"duration":0,"x":232.56,"y":63.27}]},{"name":"bone9","translateFrame":[{"duration":10,"tweenEasing":0},{"duration":10,"tweenEasing":0,"x":125.52,"y":132.39},{"duration":5,"tweenEasing":0,"x":116.49,"y":8.96},{"duration":10,"tweenEasing":0,"x":152.34,"y":126.4},{"duration":0,"x":141.96,"y":8.96}]},{"name":"bone10","translateFrame":[{"duration":10,"tweenEasing":0},{"duration":10,"tweenEasing":0,"x":180.64,"y":145.95},{"duration":5,"tweenEasing":0,"x":52.01,"y":84.44},{"duration":10,"tweenEasing":0,"x":207.46,"y":139.97},{"duration":0,"x":77.49,"y":84.44}]},{"name":"bone11","translateFrame":[{"duration":10,"tweenEasing":0},{"duration":10,"tweenEasing":0,"x":227.28,"y":123.06},{"duration":5,"tweenEasing":0,"x":353.98,"y":91.02},{"duration":10,"tweenEasing":0,"x":254.1,"y":117.07},{"duration":0,"x":379.45,"y":91.02}]},{"name":"y_1","translateFrame":[{"duration":15,"tweenEasing":0},{"duration":3,"tweenEasing":0,"x":8.95,"y":-87.86},{"duration":17,"x":8.94,"y":7.61}],"scaleFrame":[{"duration":15,"tweenEasing":0},{"duration":20,"x":-0.9,"y":0.9}]},{"name":"y_1_1","translateFrame":[{"duration":20,"tweenEasing":0},{"duration":5,"tweenEasing":0,"x":8.95,"y":7.64},{"duration":10,"x":8.95,"y":50.5}],"scaleFrame":[{"duration":20,"tweenEasing":0},{"duration":5,"tweenEasing":0,"x":-0.9,"y":0.9},{"duration":10,"x":-2.5,"y":2.5}]},{"name":"y_2","translateFrame":[{"duration":3,"tweenEasing":0,"x":-17.54,"y":-87.03},{"duration":32,"x":-17.55,"y":-0.5}],"scaleFrame":[{"duration":35,"x":-0.9,"y":0.9}]},{"name":"y_2_2","translateFrame":[{"duration":5,"tweenEasing":0},{"duration":5,"tweenEasing":0,"x":-17.26,"y":-0.37},{"duration":25,"x":-17.26,"y":39.86}],"scaleFrame":[{"duration":5,"tweenEasing":0},{"duration":5,"tweenEasing":0,"x":-0.9,"y":0.9},{"duration":25,"x":-2.5,"y":2.5}]}],"slot":[{"name":"xxxx_1","displayFrame":[{"duration":5,"value":-1},{"duration":10,"value":1},{"duration":5,"value":-1},{"duration":10,"value":1},{"duration":5,"value":-1}],"colorFrame":[{"duration":10,"tweenEasing":0},{"duration":5,"tweenEasing":0},{"duration":5,"tweenEasing":0,"value":{"aM":0}},{"duration":5,"tweenEasing":0},{"duration":5,"tweenEasing":0},{"duration":5,"value":{"aM":0}}]},{"name":"xxxx_7","displayFrame":[{"duration":5,"value":-1},{"duration":10,"value":1},{"duration":5,"value":-1},{"duration":10,"value":1},{"duration":5,"value":-1}],"colorFrame":[{"duration":10,"tweenEasing":0},{"duration":5,"tweenEasing":0},{"duration":5,"tweenEasing":0,"value":{"aM":0}},{"duration":5,"tweenEasing":0},{"duration":5,"tweenEasing":0},{"duration":5,"value":{"aM":0}}]},{"name":"xxxx_8","displayFrame":[{"duration":5,"value":-1},{"duration":10,"value":1},{"duration":5,"value":-1},{"duration":10,"value":1},{"duration":5,"value":-1}],"colorFrame":[{"duration":10,"tweenEasing":0},{"duration":5,"tweenEasing":0},{"duration":5,"tweenEasing":0,"value":{"aM":0}},{"duration":5,"tweenEasing":0},{"duration":5,"tweenEasing":0},{"duration":5,"value":{"aM":0}}]},{"name":"xxxx_9","displayFrame":[{"duration":5,"value":-1},{"duration":10,"value":1},{"duration":5,"value":-1},{"duration":10,"value":1},{"duration":5,"value":-1}],"colorFrame":[{"duration":10,"tweenEasing":0},{"duration":5,"tweenEasing":0},{"duration":5,"tweenEasing":0,"value":{"aM":0}},{"duration":5,"tweenEasing":0},{"duration":5,"tweenEasing":0},{"duration":5,"value":{"aM":0}}]},{"name":"xxxx_10","displayFrame":[{"duration":10,"value":-1},{"duration":10,"value":1},{"duration":5,"value":-1},{"duration":10,"value":1},{"duration":0,"value":-1}],"colorFrame":[{"duration":15,"tweenEasing":0},{"duration":5,"tweenEasing":0},{"duration":5,"tweenEasing":0,"value":{"aM":0}},{"duration":5,"tweenEasing":0},{"duration":5,"tweenEasing":0},{"duration":0,"value":{"aM":0}}]},{"name":"xxxx_11","displayFrame":[{"duration":10,"value":-1},{"duration":10,"value":1},{"duration":5,"value":-1},{"duration":10,"value":1},{"duration":0,"value":-1}],"colorFrame":[{"duration":15,"tweenEasing":0},{"duration":5,"tweenEasing":0},{"duration":5,"tweenEasing":0,"value":{"aM":0}},{"duration":5,"tweenEasing":0},{"duration":5,"tweenEasing":0},{"duration":0,"value":{"aM":0}}]},{"name":"xxxx_12","displayFrame":[{"duration":10,"value":-1},{"duration":10,"value":1},{"duration":5,"value":-1},{"duration":10,"value":1},{"duration":0,"value":-1}],"colorFrame":[{"duration":15,"tweenEasing":0},{"duration":5,"tweenEasing":0},{"duration":5,"tweenEasing":0,"value":{"aM":0}},{"duration":5,"tweenEasing":0},{"duration":5,"tweenEasing":0},{"duration":0,"value":{"aM":0}}]},{"name":"xxxx_13","displayFrame":[{"duration":10,"value":-1},{"duration":10,"value":1},{"duration":5,"value":-1},{"duration":10,"value":1},{"duration":0,"value":-1}],"colorFrame":[{"duration":15,"tweenEasing":0},{"duration":5,"tweenEasing":0},{"duration":5,"tweenEasing":0,"value":{"aM":0}},{"duration":5,"tweenEasing":0},{"duration":5,"tweenEasing":0},{"duration":0,"value":{"aM":0}}]},{"name":"yl_1","displayFrame":[{"duration":15,"value":-1},{"duration":20}],"colorFrame":[{"duration":15,"tweenEasing":0},{"duration":3,"tweenEasing":0,"value":{"aM":0}},{"duration":17}]},{"name":"yl_2","displayFrame":[{"duration":20,"value":-1},{"duration":15}],"colorFrame":[{"duration":22,"tweenEasing":0},{"duration":3,"tweenEasing":0},{"duration":10,"value":{"aM":0}}]},{"name":"yl_3","displayFrame":[{"duration":35}],"colorFrame":[{"duration":3,"tweenEasing":0,"value":{"aM":0}},{"duration":32}]},{"name":"yl_4","displayFrame":[{"duration":5,"value":-1},{"duration":30}],"colorFrame":[{"duration":7,"tweenEasing":0},{"duration":3,"tweenEasing":0},{"duration":25,"value":{"aM":0}}]}]}],"defaultActions":[{"gotoAndPlay":"attack_j_1"}]}]}